Workbook
Name IQ_CH: 110000
Name IQ_CQ: 5000
Name IQ_CY: 10000
Name IQ_DAILY: 500000
Name IQ_FH: 100000
Name IQ_FQ: 500
Name IQ_FY: 1000
Name IQ_LTM: 2000
Name IQ_MONTH: 15000
Name IQ_NTM: 6000
Name IQ_WEEK: 50000
Name IQ_YTD: 3000

Sheet Football field
B3: Synthesis of results
B6: Enterprise value
B8: EUR/000 | C8: Min | D8: Centre | E8: Max | G8: Football field | Enterprise Value
B10: Discounted Cash Flow | C10: =+MIN(DCF!D86:F88) -> 61654.942 | D10: =+DCF!C66 -> 69373.448 | E10: =+MAX(DCF!D86:F88) -> 79514.461
B11: Income method | C11: =+MIN('Income method'!D78:F80) -> 67995.321 | D11: =+'Income method'!C58 -> 76454.971 | E11: =+MAX('Income method'!D78:F80) -> 87575.324
B12: EVA | C12: =+MIN('Patrimoniale e misto'!D87:F89) -> 53498.193 | D12: =+'Patrimoniale e misto'!C73 -> 54667.351 | E12: =+MAX('Patrimoniale e misto'!D87:F89) -> 55863.016
B13: Metodi patrimoniali | C13: =+MIN('Patrimoniale e misto'!C10,'Patrimoniale e misto'!F28) -> 50925 | D13: =+AVERAGE(C13,E13) -> 51448 | E13: =+MAX('Patrimoniale e misto'!C10,'Patrimoniale e misto'!F28) -> 51971
B14: Transaction multiples | C14: =+'Multipli di transazioni'!C47 -> 54449.319 | D14: =+'Multipli di transazioni'!D47 -> 62357.969 | E14: =+'Multipli di transazioni'!E47 -> 63302.718
B15: Market multiples | C15: =+MIN('Multipli di borsa'!C40:D40) -> 59750.136 | D15: =+AVERAGE(C15,E15) -> 62070.361 | E15: =+MAX('Multipli di borsa'!C40:D40) -> 64390.585
B18: EV / EBITDA 2020
B20: EBITDA 2020 | C20: =+Proiezioni!$F$22 -> 12100 | D20: =+Proiezioni!$F$22 -> 12100 | E20: =+Proiezioni!$F$22 -> 12100
C22: Min | D22: Centre | E22: Max | G22: Football field | EV / EBITDA
B24: Discounted Cash Flow | C24: =+C10/C$20 -> 5.0954498 | D24: =+D10/D$20 -> 5.7333428 | E24: =+E10/E$20 -> 6.5714431
B25: Income method | C25: =+C11/C$20 -> 5.619448 | D25: =+D11/D$20 -> 6.3185927 | E25: =+E11/E$20 -> 7.2376301
B26: EVA | C26: =+C12/C$20 -> 4.4213383 | D26: =+D12/D$20 -> 4.5179629 | E26: =+E12/E$20 -> 4.6167782
B27: Metodi patrimoniali | C27: =+C13/C$20 -> 4.2086777 | D27: =+D13/D$20 -> 4.2519008 | E27: =+E13/E$20 -> 4.295124
B28: Transaction multiples | C28: =+C14/C$20 -> 4.4999437 | D28: =+D14/D$20 -> 5.1535512 | E28: =+E14/E$20 -> 5.2316296
B29: Market multiples | C29: =+C15/C$20 -> 4.9380278 | D29: =+D15/D$20 -> 5.1297819 | E29: =+E15/E$20 -> 5.321536
B32: Equity value
B34: EUR/000 | C34: Min | D34: Centre | E34: Max | G34: Football field | Equity Value
B36: Discounted Cash Flow | C36: =+MIN(DCF!D95:F97) -> 45358.942 | D36: =+DCF!C79 -> 53077.448 | E36: =+MAX(DCF!D95:F97) -> 63218.461
B37: Income method | C37: =+MIN('Income method'!D87:F89) -> 51699.321 | D37: =+'Income method'!C71 -> 60158.971 | E37: =+MAX('Income method'!D87:F89) -> 71279.324
B38: EVA | C38: =+MIN('Patrimoniale e misto'!D96:F98) -> 39034.193 | D38: =+'Patrimoniale e misto'!C80 -> 40203.351 | E38: =+MAX('Patrimoniale e misto'!D96:F98) -> 41399.016
B39: Metodi patrimoniali | C39: =+MIN('Patrimoniale e misto'!C17,'Patrimoniale e misto'!F35) -> 36461 | D39: =+AVERAGE(C39,E39) -> 36984 | E39: =+MAX('Patrimoniale e misto'!C17,'Patrimoniale e misto'!F35) -> 37507
B40: Transaction multiples | C40: =+'Multipli di transazioni'!C54 -> 39985.319 | D40: =+'Multipli di transazioni'!D54 -> 47893.969 | E40: =+'Multipli di transazioni'!E54 -> 48838.718
B41: Market multiples | C41: =+MIN('Multipli di borsa'!C47:D47) -> 45286.136 | D41: =+AVERAGE(C41,E41) -> 47606.361 | E41: =+MAX('Multipli di borsa'!C47:D47) -> 49926.585
B45: Charts | EV
B46: Discounted Cash Flow | C46: =+C10/1000 -> 61.654942 | D46: =(D10-C10)/1000 -> 7.7185059 | E46: =(E10-D10)/1000 -> 10.141013 | F46: =+E10/1000 -> 79.514461
B47: Income method | C47: =+C11/1000 -> 67.995321 | D47: =(D11-C11)/1000 -> 8.4596498 | E47: =(E11-D11)/1000 -> 11.120353 | F47: =+E11/1000 -> 87.575324
B48: EVA | C48: =+C12/1000 -> 53.498193 | D48: =(D12-C12)/1000 -> 1.1691578 | E48: =(E12-D12)/1000 -> 1.1956653 | F48: =+E12/1000 -> 55.863016
B49: Metodi patrimoniali | C49: =+C13/1000 -> 50.925 | D49: =(D13-C13)/1000 -> 0.523 | E49: =(E13-D13)/1000 -> 0.523 | F49: =+E13/1000 -> 51.971
B50: Transaction multiples | C50: =+C14/1000 -> 54.449319 | D50: =(D14-C14)/1000 -> 7.9086501 | E50: =(E14-D14)/1000 -> 0.94474901 | F50: =+E14/1000 -> 63.302718
B51: Market multiples | C51: =+C15/1000 -> 59.750136 | D51: =(D15-C15)/1000 -> 2.3202246 | E51: =(E15-D15)/1000 -> 2.3202246 | F51: =+E15/1000 -> 64.390585
B53: Charts | EV/EBITDA
B54: Discounted Cash Flow | C54: =+C24 -> 5.0954498 | D54: =(D24-C24) -> 0.63789305 | E54: =(E24-D24) -> 0.83810027 | F54: =+E24 -> 6.5714431
B55: Income method | C55: =+C25 -> 5.619448 | D55: =(D25-C25) -> 0.69914461 | E55: =(E25-D25) -> 0.91903742 | F55: =+E25 -> 7.2376301
B56: EVA | C56: =+C26 -> 4.4213383 | D56: =(D26-C26) -> 0.09662461 | E56: =(E26-D26) -> 0.098815313 | F56: =+E26 -> 4.6167782
B57: Metodi patrimoniali | C57: =+C27 -> 4.2086777 | D57: =(D27-C27) -> 0.04322314 | E57: =(E27-D27) -> 0.04322314 | F57: =+E27 -> 4.295124
B58: Transaction multiples | C58: =+C28 -> 4.4999437 | D58: =(D28-C28) -> 0.65360744 | E58: =(E28-D28) -> 0.07807843 | F58: =+E28 -> 5.2316296
B59: Market multiples | C59: =+C29 -> 4.9380278 | D59: =(D29-C29) -> 0.1917541 | E59: =(E29-D29) -> 0.1917541 | F59: =+E29 -> 5.321536
B61: Charts | Equity value
B62: Discounted Cash Flow | C62: =+C36/1000 -> 45.358942 | D62: =(D36-C36)/1000 -> 7.7185059 | E62: =(E36-D36)/1000 -> 10.141013 | F62: =+E36/1000 -> 63.218461
B63: Income method | C63: =+C37/1000 -> 51.699321 | D63: =(D37-C37)/1000 -> 8.4596498 | E63: =(E37-D37)/1000 -> 11.120353 | F63: =+E37/1000 -> 71.279324
B64: EVA | C64: =+C38/1000 -> 39.034193 | D64: =(D38-C38)/1000 -> 1.1691578 | E64: =(E38-D38)/1000 -> 1.1956653 | F64: =+E38/1000 -> 41.399016
B65: Metodi patrimoniali | C65: =+C39/1000 -> 36.461 | D65: =(D39-C39)/1000 -> 0.523 | E65: =(E39-D39)/1000 -> 0.523 | F65: =+E39/1000 -> 37.507
B66: Transaction multiples | C66: =+C40/1000 -> 39.985319 | D66: =(D40-C40)/1000 -> 7.9086501 | E66: =(E40-D40)/1000 -> 0.94474901 | F66: =+E40/1000 -> 48.838718
B67: Market multiples | C67: =+C41/1000 -> 45.286136 | D67: =(D41-C41)/1000 -> 2.3202246 | E67: =(E41-D41)/1000 -> 2.3202246 | F67: =+E41/1000 -> 49.926585

Sheet DCF
B3: Discounted cash flow
B6: Control panel
B7: Period | C7: 0.5
B8: WACC | C8: 0.07
B9: LT g rate | C9: 0.015
B10: IRES | C10: 0.24
B11: IRAP | C11: 0.039
B13: Discounted cash flow
B15: EUR/000 | C15: =+'Actual data'!G8 -> 2017 | D15: =+C15+1 -> 2018 | E15: =+D15+1 -> 2019 | F15: =+E15+1 -> 2020 | G15: =+F15+1 -> 2021 | H15: =+G15+1 -> 2022 | I15: =+H15+1 -> 2023 | J15: =+I15+1 -> 2024 | K15: TV
B17: Ricavi | C17: =+Proiezioni!C10 -> 29488 | D17: =+Proiezioni!D10 -> 31352 | E17: =+Proiezioni!E10 -> 32326 | F17: =+Proiezioni!F10 -> 33000 | G17: =+Proiezioni!G10 -> 33500 | H17: =+Proiezioni!H10 -> 33750 | I17: =+Proiezioni!I10 -> 34500 | J17: =+Proiezioni!J10 -> 34750 | K17: =+J17*(1+$C$9) -> 35271.25
B18: Altri Ricavi | C18: =+Proiezioni!C11 -> 126 | D18: =+Proiezioni!D11 -> 0 | E18: =+Proiezioni!E11 -> 48 | F18: =+Proiezioni!F11 -> 0 | G18: =+Proiezioni!G11 -> 0 | H18: =+Proiezioni!H11 -> 0 | I18: =+Proiezioni!I11 -> 0 | J18: =+Proiezioni!J11 -> 0 | K18: =+J18*(1+$C$9) -> 0
B19: Valore della produzione | C19: =+SUM(C17:C18) -> 29614 | D19: =+SUM(D17:D18) -> 31352 | E19: =+SUM(E17:E18) -> 32374 | F19: =+SUM(F17:F18) -> 33000 | G19: =+SUM(G17:G18) -> 33500 | H19: =+SUM(H17:H18) -> 33750 | I19: =+SUM(I17:I18) -> 34500 | J19: =+SUM(J17:J18) -> 34750 | K19: =+SUM(K17:K18) -> 35271.25
B20: YoY Delta | C20: =+IFERROR(C19/#REF!-1,"n.a.") -> n.a. | D20: =+IFERROR(D19/C19-1,"n.a.") -> 0.058688458 | E20: =+IFERROR(E19/D19-1,"n.a.") -> 0.032597601 | F20: =+IFERROR(F19/E19-1,"n.a.") -> 0.019336505 | G20: =+IFERROR(G19/F19-1,"n.a.") -> 0.015151515 | H20: =+IFERROR(H19/G19-1,"n.a.") -> 0.0074626866 | I20: =+IFERROR(I19/H19-1,"n.a.") -> 0.022222222 | J20: =+IFERROR(J19/I19-1,"n.a.") -> 0.0072463768 | K20: =+IFERROR(K19/J19-1,"n.a.") -> 0.015
B22: Costo delle materie prime | C22: =+Proiezioni!C15 -> -710 | D22: =+Proiezioni!D15 -> -775 | E22: =+Proiezioni!E15 -> -882 | F22: =+Proiezioni!F15 -> -900 | G22: =+Proiezioni!G15 -> -910 | H22: =+Proiezioni!H15 -> -920 | I22: =+Proiezioni!I15 -> -930 | J22: =+Proiezioni!J15 -> -940 | K22: =+J22*(1+$C$9) -> -954.1
B23: Variazione materie prime | C23: =+Proiezioni!C16 -> 0 | D23: =+Proiezioni!D16 -> 0 | E23: =+Proiezioni!E16 -> 0 | F23: =+Proiezioni!F16 -> 0 | G23: =+Proiezioni!G16 -> 0 | H23: =+Proiezioni!H16 -> 0 | I23: =+Proiezioni!I16 -> 0 | J23: =+Proiezioni!J16 -> 0 | K23: =+J23*(1+$C$9) -> 0
B24: Costi per servizi | C24: =+Proiezioni!C17 -> -9650 | D24: =+Proiezioni!D17 -> -11396 | E24: =+Proiezioni!E17 -> -11688 | F24: =+Proiezioni!F17 -> -12600 | G24: =+Proiezioni!G17 -> -12800 | H24: =+Proiezioni!H17 -> -12900 | I24: =+Proiezioni!I17 -> -13100 | J24: =+Proiezioni!J17 -> -13150 | K24: =+J24*(1+$C$9) -> -13347.25
B25: Costo del personale | C25: =+Proiezioni!C18 -> -5041 | D25: =+Proiezioni!D18 -> -5577 | E25: =+Proiezioni!E18 -> -6083 | F25: =+Proiezioni!F18 -> -5600 | G25: =+Proiezioni!G18 -> -5600 | H25: =+Proiezioni!H18 -> -5650 | I25: =+Proiezioni!I18 -> -5675 | J25: =+Proiezioni!J18 -> -5700 | K25: =+J25*(1+$C$9) -> -5785.5
B26: Oneri diversi di gestione | C26: =+Proiezioni!C19 -> -1989 | D26: =+Proiezioni!D19 -> -1665 | E26: =+Proiezioni!E19 -> -1803 | F26: =+Proiezioni!F19 -> -1800 | G26: =+Proiezioni!G19 -> -1800 | H26: =+Proiezioni!H19 -> -1800 | I26: =+Proiezioni!I19 -> -1800 | J26: =+Proiezioni!J19 -> -1800 | K26: =+J26*(1+$C$9) -> -1827
B27: Costi operativi | C27: =+SUM(C22:C26) -> -17390 | D27: =+SUM(D22:D26) -> -19413 | E27: =+SUM(E22:E26) -> -20456 | F27: =+SUM(F22:F26) -> -20900 | G27: =+SUM(G22:G26) -> -21110 | H27: =+SUM(H22:H26) -> -21270 | I27: =+SUM(I22:I26) -> -21505 | J27: =+SUM(J22:J26) -> -21590 | K27: =+SUM(K22:K26) -> -21913.85
B29: EBITDA | C29: =+C19+C27 -> 12224 | D29: =+D19+D27 -> 11939 | E29: =+E19+E27 -> 11918 | F29: =+F19+F27 -> 12100 | G29: =+G19+G27 -> 12390 | H29: =+H19+H27 -> 12480 | I29: =+I19+I27 -> 12995 | J29: =+J19+J27 -> 13160 | K29: =+K19+K27 -> 13357.4
B30: % Ricavi | C30: =+C29/C$19 -> 0.41277774 | D30: =+D29/D$19 -> 0.38080505 | E30: =+E29/E$19 -> 0.36813492 | F30: =+F29/F$19 -> 0.36666667 | G30: =+G29/G$19 -> 0.36985075 | H30: =+H29/H$19 -> 0.36977778 | I30: =+I29/I$19 -> 0.37666667 | J30: =+J29/J$19 -> 0.37870504 | K30: =+K29/K$19 -> 0.37870504
B32: D&A | C32: =+Proiezioni!C25 -> -6532 | D32: =+Proiezioni!D25 -> -6034 | E32: =+Proiezioni!E25 -> -6193 | F32: =+Proiezioni!F25 -> -6250 | G32: =+Proiezioni!G25 -> -6400 | H32: =+Proiezioni!H25 -> -6500 | I32: =+Proiezioni!I25 -> -6550 | J32: =+Proiezioni!J25 -> -6600 | K32: =+K46 -> -7400
B33: Accantonamenti | C33: =+Proiezioni!C26 -> -60 | D33: =+Proiezioni!D26 -> 0 | E33: =+Proiezioni!E26 -> 0 | F33: =+Proiezioni!F26 -> 0 | G33: =+Proiezioni!G26 -> 0 | H33: =+Proiezioni!H26 -> 0 | I33: =+Proiezioni!I26 -> 0 | J33: =+Proiezioni!J26 -> 0 | K33: =+K48 -> 0
B35: EBIT | C35: =+C29+SUM(C32:C33) -> 5632 | D35: =+D29+SUM(D32:D33) -> 5905 | E35: =+E29+SUM(E32:E33) -> 5725 | F35: =+F29+SUM(F32:F33) -> 5850 | G35: =+G29+SUM(G32:G33) -> 5990 | H35: =+H29+SUM(H32:H33) -> 5980 | I35: =+I29+SUM(I32:I33) -> 6445 | J35: =+J29+SUM(J32:J33) -> 6560 | K35: =+K29+SUM(K32:K33) -> 5957.4
B36: % Ricavi | C36: =+C35/C$19 -> 0.19018032 | D36: =+D35/D$19 -> 0.18834524 | E36: =+E35/E$19 -> 0.17683944 | F36: =+F35/F$19 -> 0.17727273 | G36: =+G35/G$19 -> 0.17880597 | H36: =+H35/H$19 -> 0.17718519 | I36: =+I35/I$19 -> 0.18681159 | J36: =+J35/J$19 -> 0.18877698 | K36: =+K35/K$19 -> 0.16890243
B38: IRAP | C38: =+MIN(0,-C35*$C$11) -> -219.648 | D38: =+MIN(0,-D35*$C$11) -> -230.295 | E38: =+MIN(0,-E35*$C$11) -> -223.275 | F38: =+MIN(0,-F35*$C$11) -> -228.15 | G38: =+MIN(0,-G35*$C$11) -> -233.61 | H38: =+MIN(0,-H35*$C$11) -> -233.22 | I38: =+MIN(0,-I35*$C$11) -> -251.355 | J38: =+MIN(0,-J35*$C$11) -> -255.84 | K38: =+MIN(0,-K35*$C$11) -> -232.3386
B39: IRES | C39: =+MIN(0,-(C35+C38*0.1)*$C$10) -> -1346.4084 | D39: =+MIN(0,-(D35+D38*0.1)*$C$10) -> -1411.6729 | E39: =+MIN(0,-(E35+E38*0.1)*$C$10) -> -1368.6414 | F39: =+MIN(0,-(F35+F38*0.1)*$C$10) -> -1398.5244 | G39: =+MIN(0,-(G35+G38*0.1)*$C$10) -> -1431.9934 | H39: =+MIN(0,-(H35+H38*0.1)*$C$10) -> -1429.6027 | I39: =+MIN(0,-(I35+I38*0.1)*$C$10) -> -1540.7675 | J39: =+MIN(0,-(J35+J38*0.1)*$C$10) -> -1568.2598 | K39: =+MIN(0,-(K35+K38*0.1)*$C$10) -> -1424.1999
B40: Imposte figurative | C40: =+SUM(C38:C39) -> -1566.0564 | D40: =+SUM(D38:D39) -> -1641.9679 | E40: =+SUM(E38:E39) -> -1591.9164 | F40: =+SUM(F38:F39) -> -1626.6744 | G40: =+SUM(G38:G39) -> -1665.6034 | H40: =+SUM(H38:H39) -> -1662.8227 | I40: =+SUM(I38:I39) -> -1792.1225 | J40: =+SUM(J38:J39) -> -1824.0998 | K40: =+SUM(K38:K39) -> -1656.5385
B42: NOPAT | C42: =+C35+C40 -> 4065.9436 | D42: =+D35+D40 -> 4263.0321 | E42: =+E35+E40 -> 4133.0836 | F42: =+F35+F40 -> 4223.3256 | G42: =+G35+G40 -> 4324.3966 | H42: =+H35+H40 -> 4317.1773 | I42: =+I35+I40 -> 4652.8775 | J42: =+J35+J40 -> 4735.9002 | K42: =+K35+K40 -> 4300.8615
B44: D&A add-back | F44: =+-SUM(F32:F33) -> 6250 | G44: =+-SUM(G32:G33) -> 6400 | H44: =+-SUM(H32:H33) -> 6500 | I44: =+-SUM(I32:I33) -> 6550 | J44: =+-SUM(J32:J33) -> 6600 | K44: =+-SUM(K32:K33) -> 7400
B45: Delta in NWC | F45: =+Proiezioni!F89 -> -8.3105194 | G45: =+Proiezioni!G89 -> -237.13763 | H45: =+Proiezioni!H89 -> -116.39599 | I45: =+Proiezioni!I89 -> -401.33576 | J45: =+Proiezioni!J89 -> -138.12423 | K45: =-Proiezioni!J57*DCF!C9 -> -180.81456
B46: Capex | F46: =+Proiezioni!F90 -> -7000 | G46: =+Proiezioni!G90 -> -7000 | H46: =+Proiezioni!H90 -> -7000 | I46: =+Proiezioni!I90 -> -9000 | J46: =+Proiezioni!J90 -> -7000 | K46: =+AVERAGE(F46:J46) -> -7400
B47: Delta in altre attività/passività | F47: =+Proiezioni!F91 -> 0 | G47: =+Proiezioni!G91 -> 0 | H47: =+Proiezioni!H91 -> 0 | I47: =+Proiezioni!I91 -> 0 | J47: =+Proiezioni!J91 -> 0 | K47: =+Proiezioni!K91 -> 0
B48: Fondi | F48: =+Proiezioni!F92 -> 0 | G48: =+Proiezioni!G92 -> 0 | H48: =+Proiezioni!H92 -> 0 | I48: =+Proiezioni!I92 -> 0 | J48: =+Proiezioni!J92 -> 0 | K48: =+Proiezioni!K92 -> 0
B50: Free cash flows | F50: =+F42+SUM(F44:F48) -> 3465.0151 | G50: =+G42+SUM(G44:G48) -> 3487.259 | H50: =+H42+SUM(H44:H48) -> 3700.7813 | I50: =+I42+SUM(I44:I48) -> 1801.5418 | J50: =+J42+SUM(J44:J48) -> 4197.7759 | K50: =+K42+SUM(K44:K48) -> 4120.047
B52: Period | F52: =+$C$7 -> 0.5 | G52: =+F52+1 -> 1.5 | H52: =+G52+1 -> 2.5 | I52: =+H52+1 -> 3.5 | J52: =+I52+1 -> 4.5
B53: Discount factor | F53: =1/(1+$C$8)^F52 -> 0.96673649 | G53: =1/(1+$C$8)^G52 -> 0.90349205 | H53: =1/(1+$C$8)^H52 -> 0.84438509 | I53: =1/(1+$C$8)^I52 -> 0.78914494 | J53: =1/(1+$C$8)^J52 -> 0.73751864
B55: Discounted FCF | F55: =+F50*F53 -> 3349.7565 | G55: =+G50*G53 -> 3150.7108 | H55: =+H50*H53 -> 3124.8845 | I55: =+I50*I53 -> 1421.6776 | J55: =+J50*J53 -> 3095.938
B58: ∑ of Discounted FCF | C58: =+SUM(F55:J55) -> 14142.967
B60: Terminal flow | C60: =+K50 -> 4120.047
B61: Undiscounted TV | C61: =+C60/(C8-C9) -> 74909.945
B62: Terminal Value | C62: =+C61*J53 -> 55247.481
B64: Fondi | C64: =Proiezioni!E61 -> -17
B66: Enterprise Value | C66: =+C58+C62+C64 -> 69373.448
B68: Bridge to Equity
B69: Passività finanziarie | C69: =+Proiezioni!E67 -> 14006
B70: Passività finanziarie - IC | C70: =+Proiezioni!E68 -> 68813
B71: TFR | C71: =+Proiezioni!E69 -> 1310
B72: Attività finanziarie | C72: =+Proiezioni!E70 -> -23165
B73: Attività finanziarie - IC | C73: =+Proiezioni!E71 -> 0
B74: Cash and cash equivalents | C74: =+Proiezioni!E72 -> -101
B75: Posizione finanziaria netta | C75: =+SUM(C69:C74) -> 60863
B77: Partecipazioni | C77: =+Proiezioni!E75 -> -44567
B79: Equity Value | C79: =+C66-C75-C77 -> 53077.448
C82: Sensitivity analysis | Enterprise Value
F84: WACC
B85: LT g rate | C85: =+C66 -> 69373.448 | D85: 0.065 | E85: 0.07 | F85: 0.075
C86: 0.0125 | D86: 73485.06 | E86: 67053.268 | F86: 61654.942
C87: 0.015 | D87: 76349.026 | E87: 69373.448 | F87: 63564.858
C88: 0.0175 | D88: 79514.461 | E88: 71914.597 | F88: 65640.853
C91: Sensitivity analysis | Equity Value
F93: WACC
B94: LT g rate | C94: =+C79 -> 53077.448 | D94: 0.065 | E94: 0.07 | F94: 0.075
C95: 0.0125 | D95: 57189.06 | E95: 50757.268 | F95: 45358.942
C96: 0.015 | D96: 60053.026 | E96: 53077.448 | F96: 47268.858
C97: 0.0175 | D97: 63218.461 | E97: 55618.597 | F97: 49344.853

Sheet Income method
B3: Income method
B6: Control panel
B7: Period | C7: 0.5
B8: WACC | C8: 0.07
B9: LT g rate | C9: 0.015
B10: IRES | C10: 0.24
B11: IRAP | C11: 0.039
B13: Income method
B15: EUR/000 | C15: =+'Actual data'!G8 -> 2017 | D15: =+C15+1 -> 2018 | E15: =+D15+1 -> 2019 | F15: =+E15+1 -> 2020 | G15: =+F15+1 -> 2021 | H15: =+G15+1 -> 2022 | I15: =+H15+1 -> 2023 | J15: =+I15+1 -> 2024 | K15: TV
B17: Ricavi | C17: =+Proiezioni!C10 -> 29488 | D17: =+Proiezioni!D10 -> 31352 | E17: =+Proiezioni!E10 -> 32326 | F17: =+Proiezioni!F10 -> 33000 | G17: =+Proiezioni!G10 -> 33500 | H17: =+Proiezioni!H10 -> 33750 | I17: =+Proiezioni!I10 -> 34500 | J17: =+Proiezioni!J10 -> 34750 | K17: =+J17*(1+$C$9) -> 35271.25
B18: Altri ricavi | C18: =+Proiezioni!C11 -> 126 | D18: =+Proiezioni!D11 -> 0 | E18: =+Proiezioni!E11 -> 48 | F18: =+Proiezioni!F11 -> 0 | G18: =+Proiezioni!G11 -> 0 | H18: =+Proiezioni!H11 -> 0 | I18: =+Proiezioni!I11 -> 0 | J18: =+Proiezioni!J11 -> 0 | K18: =+J18*(1+$C$9) -> 0
B19: Valore della produzione | C19: =+SUM(C17:C18) -> 29614 | D19: =+SUM(D17:D18) -> 31352 | E19: =+SUM(E17:E18) -> 32374 | F19: =+SUM(F17:F18) -> 33000 | G19: =+SUM(G17:G18) -> 33500 | H19: =+SUM(H17:H18) -> 33750 | I19: =+SUM(I17:I18) -> 34500 | J19: =+SUM(J17:J18) -> 34750 | K19: =+SUM(K17:K18) -> 35271.25
B20: YoY Delta | C20: =+IFERROR(C19/#REF!-1,"n.a.") -> n.a. | D20: =+IFERROR(D19/C19-1,"n.a.") -> 0.058688458 | E20: =+IFERROR(E19/D19-1,"n.a.") -> 0.032597601 | F20: =+IFERROR(F19/E19-1,"n.a.") -> 0.019336505 | G20: =+IFERROR(G19/F19-1,"n.a.") -> 0.015151515 | H20: =+IFERROR(H19/G19-1,"n.a.") -> 0.0074626866 | I20: =+IFERROR(I19/H19-1,"n.a.") -> 0.022222222 | J20: =+IFERROR(J19/I19-1,"n.a.") -> 0.0072463768 | K20: =+IFERROR(K19/J19-1,"n.a.") -> 0.015
B22: Costo delle materie prime | C22: =+Proiezioni!C15 -> -710 | D22: =+Proiezioni!D15 -> -775 | E22: =+Proiezioni!E15 -> -882 | F22: =+Proiezioni!F15 -> -900 | G22: =+Proiezioni!G15 -> -910 | H22: =+Proiezioni!H15 -> -920 | I22: =+Proiezioni!I15 -> -930 | J22: =+Proiezioni!J15 -> -940 | K22: =+J22*(1+$C$9) -> -954.1
B23: Variazione materie prime | C23: =+Proiezioni!C16 -> 0 | D23: =+Proiezioni!D16 -> 0 | E23: =+Proiezioni!E16 -> 0 | F23: =+Proiezioni!F16 -> 0 | G23: =+Proiezioni!G16 -> 0 | H23: =+Proiezioni!H16 -> 0 | I23: =+Proiezioni!I16 -> 0 | J23: =+Proiezioni!J16 -> 0 | K23: =+J23*(1+$C$9) -> 0
B24: Costi per servizi | C24: =+Proiezioni!C17 -> -9650 | D24: =+Proiezioni!D17 -> -11396 | E24: =+Proiezioni!E17 -> -11688 | F24: =+Proiezioni!F17 -> -12600 | G24: =+Proiezioni!G17 -> -12800 | H24: =+Proiezioni!H17 -> -12900 | I24: =+Proiezioni!I17 -> -13100 | J24: =+Proiezioni!J17 -> -13150 | K24: =+J24*(1+$C$9) -> -13347.25
B25: Costo del personale | C25: =+Proiezioni!C18 -> -5041 | D25: =+Proiezioni!D18 -> -5577 | E25: =+Proiezioni!E18 -> -6083 | F25: =+Proiezioni!F18 -> -5600 | G25: =+Proiezioni!G18 -> -5600 | H25: =+Proiezioni!H18 -> -5650 | I25: =+Proiezioni!I18 -> -5675 | J25: =+Proiezioni!J18 -> -5700 | K25: =+J25*(1+$C$9) -> -5785.5
B26: Oneri diversi di gestione | C26: =+Proiezioni!C19 -> -1989 | D26: =+Proiezioni!D19 -> -1665 | E26: =+Proiezioni!E19 -> -1803 | F26: =+Proiezioni!F19 -> -1800 | G26: =+Proiezioni!G19 -> -1800 | H26: =+Proiezioni!H19 -> -1800 | I26: =+Proiezioni!I19 -> -1800 | J26: =+Proiezioni!J19 -> -1800 | K26: =+J26*(1+$C$9) -> -1827
B27: Costi operativi | C27: =+SUM(C22:C26) -> -17390 | D27: =+SUM(D22:D26) -> -19413 | E27: =+SUM(E22:E26) -> -20456 | F27: =+SUM(F22:F26) -> -20900 | G27: =+SUM(G22:G26) -> -21110 | H27: =+SUM(H22:H26) -> -21270 | I27: =+SUM(I22:I26) -> -21505 | J27: =+SUM(J22:J26) -> -21590 | K27: =+SUM(K22:K26) -> -21913.85
B29: EBITDA | C29: =+C19+C27 -> 12224 | D29: =+D19+D27 -> 11939 | E29: =+E19+E27 -> 11918 | F29: =+F19+F27 -> 12100 | G29: =+G19+G27 -> 12390 | H29: =+H19+H27 -> 12480 | I29: =+I19+I27 -> 12995 | J29: =+J19+J27 -> 13160 | K29: =+K19+K27 -> 13357.4
B30: % Ricavi | C30: =+C29/C$19 -> 0.41277774 | D30: =+D29/D$19 -> 0.38080505 | E30: =+E29/E$19 -> 0.36813492 | F30: =+F29/F$19 -> 0.36666667 | G30: =+G29/G$19 -> 0.36985075 | H30: =+H29/H$19 -> 0.36977778 | I30: =+I29/I$19 -> 0.37666667 | J30: =+J29/J$19 -> 0.37870504 | K30: =+K29/K$19 -> 0.37870504
B32: D&A | C32: =+Proiezioni!C25 -> -6532 | D32: =+Proiezioni!D25 -> -6034 | E32: =+Proiezioni!E25 -> -6193 | F32: =+Proiezioni!F25 -> -6250 | G32: =+Proiezioni!G25 -> -6400 | H32: =+Proiezioni!H25 -> -6500 | I32: =+Proiezioni!I25 -> -6550 | J32: =+Proiezioni!J25 -> -6600 | K32: =+AVERAGE(Proiezioni!F90:J90) -> -7400
B33: Accantonamenti | C33: =+Proiezioni!C26 -> -60 | D33: =+Proiezioni!D26 -> 0 | E33: =+Proiezioni!E26 -> 0 | F33: =+Proiezioni!F26 -> 0 | G33: =+Proiezioni!G26 -> 0 | H33: =+Proiezioni!H26 -> 0 | I33: =+Proiezioni!I26 -> 0 | J33: =+Proiezioni!J26 -> 0 | K33: 0
B35: EBIT | C35: =+C29+SUM(C32:C33) -> 5632 | D35: =+D29+SUM(D32:D33) -> 5905 | E35: =+E29+SUM(E32:E33) -> 5725 | F35: =+F29+SUM(F32:F33) -> 5850 | G35: =+G29+SUM(G32:G33) -> 5990 | H35: =+H29+SUM(H32:H33) -> 5980 | I35: =+I29+SUM(I32:I33) -> 6445 | J35: =+J29+SUM(J32:J33) -> 6560 | K35: =+K29+SUM(K32:K33) -> 5957.4
B36: % Ricavi | C36: =+C35/C$19 -> 0.19018032 | D36: =+D35/D$19 -> 0.18834524 | E36: =+E35/E$19 -> 0.17683944 | F36: =+F35/F$19 -> 0.17727273 | G36: =+G35/G$19 -> 0.17880597 | H36: =+H35/H$19 -> 0.17718519 | I36: =+I35/I$19 -> 0.18681159 | J36: =+J35/J$19 -> 0.18877698 | K36: =+K35/K$19 -> 0.16890243
B38: IRAP | C38: =+MIN(0,-C35*$C$11) -> -219.648 | D38: =+MIN(0,-D35*$C$11) -> -230.295 | E38: =+MIN(0,-E35*$C$11) -> -223.275 | F38: =+MIN(0,-F35*$C$11) -> -228.15 | G38: =+MIN(0,-G35*$C$11) -> -233.61 | H38: =+MIN(0,-H35*$C$11) -> -233.22 | I38: =+MIN(0,-I35*$C$11) -> -251.355 | J38: =+MIN(0,-J35*$C$11) -> -255.84 | K38: =+MIN(0,-K35*$C$11) -> -232.3386
B39: IRES | C39: =+MIN(0,-(C35+C38*0.1)*$C$10) -> -1346.4084 | D39: =+MIN(0,-(D35+D38*0.1)*$C$10) -> -1411.6729 | E39: =+MIN(0,-(E35+E38*0.1)*$C$10) -> -1368.6414 | F39: =+MIN(0,-(F35+F38*0.1)*$C$10) -> -1398.5244 | G39: =+MIN(0,-(G35+G38*0.1)*$C$10) -> -1431.9934 | H39: =+MIN(0,-(H35+H38*0.1)*$C$10) -> -1429.6027 | I39: =+MIN(0,-(I35+I38*0.1)*$C$10) -> -1540.7675 | J39: =+MIN(0,-(J35+J38*0.1)*$C$10) -> -1568.2598 | K39: =+MIN(0,-(K35+K38*0.1)*$C$10) -> -1424.1999
B40: Imposte figurative | C40: =+SUM(C38:C39) -> -1566.0564 | D40: =+SUM(D38:D39) -> -1641.9679 | E40: =+SUM(E38:E39) -> -1591.9164 | F40: =+SUM(F38:F39) -> -1626.6744 | G40: =+SUM(G38:G39) -> -1665.6034 | H40: =+SUM(H38:H39) -> -1662.8227 | I40: =+SUM(I38:I39) -> -1792.1225 | J40: =+SUM(J38:J39) -> -1824.0998 | K40: =+SUM(K38:K39) -> -1656.5385
B42: NOPAT | C42: =+C35+C40 -> 4065.9436 | D42: =+D35+D40 -> 4263.0321 | E42: =+E35+E40 -> 4133.0836 | F42: =+F35+F40 -> 4223.3256 | G42: =+G35+G40 -> 4324.3966 | H42: =+H35+H40 -> 4317.1773 | I42: =+I35+I40 -> 4652.8775 | J42: =+J35+J40 -> 4735.9002 | K42: =+K35+K40 -> 4300.8615
B44: Period | F44: =+$C$7 -> 0.5 | G44: =+F44+1 -> 1.5 | H44: =+G44+1 -> 2.5 | I44: =+H44+1 -> 3.5 | J44: =+I44+1 -> 4.5
B45: Discount factor | F45: =1/(1+$C$8)^F44 -> 0.96673649 | G45: =1/(1+$C$8)^G44 -> 0.90349205 | H45: =1/(1+$C$8)^H44 -> 0.84438509 | I45: =1/(1+$C$8)^I44 -> 0.78914494 | J45: =1/(1+$C$8)^J44 -> 0.73751864
B47: Discounted NOPAT | F47: =+F42*F45 -> 4082.843 | G47: =+G42*G45 -> 3907.058 | H47: =+H42*H45 -> 3645.3601 | I47: =+I42*I45 -> 3671.7948 | J47: =+J42*J45 -> 3492.8146
B50: ∑ of Discounted NOPAT | C50: =+SUM(F47:J47) -> 18799.87
B52: Terminal flow | C52: =+K42 -> 4300.8615
B53: Undiscounted TV | C53: =+C52/(C8-C9) -> 78197.482
B54: Terminal Value | C54: =+C53*J45 -> 57672.101
B56: Fondi | C56: =Proiezioni!E61 -> -17
B58: Enterprise Value | C58: =+C50+C54+C56 -> 76454.971
B60: Bridge to Equity
B61: Passività finanziarie | C61: =+Proiezioni!E67 -> 14006
B62: Passività finanziarie - IC | C62: =+Proiezioni!E68 -> 68813
B63: TFR | C63: =+Proiezioni!E69 -> 1310
B64: Attività finanziarie | C64: =+Proiezioni!E70 -> -23165
B65: Attività finanziarie - IC | C65: =+Proiezioni!E71 -> 0
B66: Cash and cash equivalents | C66: =+Proiezioni!E72 -> -101
B67: Posizione finanziaria netta | C67: =+SUM(C61:C66) -> 60863
B69: Partecipazioni | C69: =+Proiezioni!E75 -> -44567
B71: Equity Value | C71: =+C58-C67-C69 -> 60158.971
C74: Sensitivity analysis | Enterprise Value
F76: WACC
B77: LT g rate | C77: =+C58 -> 76454.971 | D77: 0.065 | E77: 0.07 | F77: 0.075
C78: 0.0125 | D78: 80362.611 | E78: 73642.84 | F78: 67995.321
C79: 0.015 | D79: 83788.65 | E79: 76454.971 | F79: 70340.522
C80: 0.0175 | D80: 87575.324 | E80: 79534.925 | F80: 72889.654
C83: Sensitivity analysis | Equity Value
F85: WACC
B86: LT g rate | C86: =+C71 -> 60158.971 | D86: 0.065 | E86: 0.07 | F86: 0.075
C87: 0.0125 | D87: 64066.611 | E87: 57346.84 | F87: 51699.321
C88: 0.015 | D88: 67492.65 | E88: 60158.971 | F88: 54044.522
C89: 0.0175 | D89: 71279.324 | E89: 63238.925 | F89: 56593.654

Sheet Patrimoniale e misto
B3: Metodi patrimoniali e misti
B6: Patrimoniale semplice
B8: EUR/000 | C8: =+Proiezioni!E45 -> 2019
B10: Capitale investito netto | C10: =+Proiezioni!E63 -> 50925
B12: (+/-) Posizione finanziaria netta | C12: =+Proiezioni!E73 -> 60863
B13: (+/-) Partecipazioni | C13: =+Proiezioni!E75 -> -44567
B14: (+/-) Imposte differite | C14: =+Proiezioni!E77 -> -1832
B15: Bridge to Equity | C15: =+SUM(C12:C14) -> 14464
B17: Equity Value | C17: =+C10-C15 -> 36461
B20: Patrimoniale complesso
B22: EUR/000 | C22: =+C8 -> 2019 | D22: Storno valori contabili | E22: Fair value | F22: 2019 Adj.
B24: Attivo fisso | C24: =+Proiezioni!E50 -> 39778 | D24: =+-M24 -> -5454 | E24: =+M25 -> 6500 | F24: =+SUM(C24:E24) -> 40824 | I24: Valore contabile impianti periziati | M24: 5454
B25: Capitale circolante netto | C25: =+Proiezioni!E57 -> 11153 | F25: =+SUM(C25:E25) -> 11153 | I25: Fair value asset periziati | M25: 6500
B26: Attività/passività non correnti | C26: =+Proiezioni!E59 -> 11 | F26: =+SUM(C26:E26) -> 11
B27: Fondi | C27: =+Proiezioni!E61 -> -17 | F27: =+SUM(C27:E27) -> -17
B28: Capitale investito netto | C28: =+SUM(C24:C27) -> 50925 | D28: =+SUM(D24:D27) -> -5454 | E28: =+SUM(E24:E27) -> 6500 | F28: =+SUM(F24:F27) -> 51971
B30: (+/-) Posizione finanziaria netta | F30: =+Proiezioni!E73 -> 60863
B31: (+/-) Partecipazioni | F31: =+Proiezioni!E75 -> -44567
B32: (+/-) Imposte differite | F32: =+Proiezioni!E77 -> -1832
B33: Bridge to Equity | F33: =+SUM(F30:F32) -> 14464
B35: Equity Value | F35: =+F28-F33 -> 37507
B38: Metodo misto unlevered (EVA)
B40: Control panel
B41: Period | C41: 0.5
B42: WACC | C42: 0.07
B43: LT g rate | C43: 0.015
B44: Excess earning period | C44: 5
B45: IRES | C45: 0.24
B46: IRAP | C46: 0.039
B48: EUR/000 | C48: =+C22 -> 2019 | D48: =+C48+1 -> 2020 | E48: =+D48+1 -> 2021 | F48: =+E48+1 -> 2022 | G48: =+F48+1 -> 2023 | H48: =+G48+1 -> 2024 | I48: =+H48+1 -> 2025 | J48: =+I48+1 -> 2026 | K48: =+J48+1 -> 2027 | ... M48: =+L48+1 -> 2029
B50: Capitale investito netto | C50: =+Proiezioni!E63 -> 50925 | D50: =+Proiezioni!F63 -> 51683.311 | E50: =+Proiezioni!G63 -> 52520.448 | F50: =+Proiezioni!H63 -> 53136.844 | G50: =+Proiezioni!I63 -> 55988.18 | H50: =+Proiezioni!J63 -> 56526.304
B51: Fair value adjustment | C51: =+M25-M24 -> 1046 | D51: =+C51-$C$51/5 -> 836.8 | E51: =+D51-$C$51/5 -> 627.6 | F51: =+E51-$C$51/5 -> 418.4 | G51: =+F51-$C$51/5 -> 209.2 | H51: =+G51-$C$51/5 -> 0
B52: Adjusted Capitale investito netto | C52: =+SUM(C50:C51) -> 51971 | D52: =+SUM(D50:D51) -> 52520.111 | E52: =+SUM(E50:E51) -> 53148.048 | F52: =+SUM(F50:F51) -> 53555.244 | G52: =+SUM(G50:G51) -> 56197.38 | H52: =+SUM(H50:H51) -> 56526.304 | I52: =+H52*(1+$C$43) -> 57374.199 | J52: =+I52*(1+$C$43) -> 58234.812 | K52: =+J52*(1+$C$43) -> 59108.334 | L52: =+K52*(1+$C$43) -> 59994.959 | M52: =+L52*(1+$C$43) -> 60894.883
B54: Theoretical return | D54: =IF(D48<=+$C$48+$C$44,D52*$C$42,0) -> 3676.4077 | E54: =IF(E48<=+$C$48+$C$44,E52*$C$42,0) -> 3720.3634 | F54: =IF(F48<=+$C$48+$C$44,F52*$C$42,0) -> 3748.8671 | G54: =IF(G48<=+$C$48+$C$44,G52*$C$42,0) -> 3933.8166 | H54: =IF(H48<=+$C$48+$C$44,H52*$C$42,0) -> 3956.8413 | I54: =IF(I48<=+$C$48+$C$44,I52*$C$42,0) -> 0 | J54: =IF(J48<=+$C$48+$C$44,J52*$C$42,0) -> 0 | K54: =IF(K48<=+$C$48+$C$44,K52*$C$42,0) -> 0 | ... M54: =IF(M48<=+$C$48+$C$44,M52*$C$42,0) -> 0
B56: EBIT | D56: =+Proiezioni!F28 -> 5850 | E56: =+Proiezioni!G28 -> 5990 | F56: =+Proiezioni!H28 -> 5980 | G56: =+Proiezioni!I28 -> 6445 | H56: =+Proiezioni!J28 -> 6560 | I56: =+H56*(1+$C$43) -> 6658.4 | J56: =+I56*(1+$C$43) -> 6758.276 | K56: =+J56*(1+$C$43) -> 6859.6501 | L56: =+K56*(1+$C$43) -> 6962.5449 | M56: =+L56*(1+$C$43) -> 7066.9831
B58: IRAP | D58: =+MIN(0,-D56*$C$46) -> -228.15 | E58: =+MIN(0,-E56*$C$46) -> -233.61 | F58: =+MIN(0,-F56*$C$46) -> -233.22 | G58: =+MIN(0,-G56*$C$46) -> -251.355 | H58: =+MIN(0,-H56*$C$46) -> -255.84 | I58: =+MIN(0,-I56*$C$46) -> -259.6776 | J58: =+MIN(0,-J56*$C$46) -> -263.57276 | K58: =+MIN(0,-K56*$C$46) -> -267.52636 | ... M58: =+MIN(0,-M56*$C$46) -> -275.61234
B59: IRES | D59: =+MIN(0,-(D56+D58*0.1)*$C$45) -> -1398.5244 | E59: =+MIN(0,-(E56+E58*0.1)*$C$45) -> -1431.9934 | F59: =+MIN(0,-(F56+F58*0.1)*$C$45) -> -1429.6027 | G59: =+MIN(0,-(G56+G58*0.1)*$C$45) -> -1540.7675 | H59: =+MIN(0,-(H56+H58*0.1)*$C$45) -> -1568.2598 | I59: =+MIN(0,-(I56+I58*0.1)*$C$45) -> -1591.7837 | J59: =+MIN(0,-(J56+J58*0.1)*$C$45) -> -1615.6605 | K59: =+MIN(0,-(K56+K58*0.1)*$C$45) -> -1639.8954 | ... M59: =+MIN(0,-(M56+M58*0.1)*$C$45) -> -1689.4612
B60: Imposte figurative | D60: =+SUM(D58:D59) -> -1626.6744 | E60: =+SUM(E58:E59) -> -1665.6034 | F60: =+SUM(F58:F59) -> -1662.8227 | G60: =+SUM(G58:G59) -> -1792.1225 | H60: =+SUM(H58:H59) -> -1824.0998 | I60: =+SUM(I58:I59) -> -1851.4613 | J60: =+SUM(J58:J59) -> -1879.2333 | K60: =+SUM(K58:K59) -> -1907.4218 | ... M60: =+SUM(M58:M59) -> -1965.0736
B62: NOPAT | D62: =IF(D48<=+$C$48+$C$44,D56+D60,0) -> 4223.3256 | E62: =IF(E48<=+$C$48+$C$44,E56+E60,0) -> 4324.3966 | F62: =IF(F48<=+$C$48+$C$44,F56+F60,0) -> 4317.1773 | G62: =IF(G48<=+$C$48+$C$44,G56+G60,0) -> 4652.8775 | H62: =IF(H48<=+$C$48+$C$44,H56+H60,0) -> 4735.9002 | I62: =IF(I48<=+$C$48+$C$44,I56+I60,0) -> 0 | J62: =IF(J48<=+$C$48+$C$44,J56+J60,0) -> 0 | K62: =IF(K48<=+$C$48+$C$44,K56+K60,0) -> 0 | ... M62: =IF(M48<=+$C$48+$C$44,M56+M60,0) -> 0
B64: Excess earnings | D64: =+D62-D54 -> 546.91786 | E64: =+E62-E54 -> 604.03327 | F64: =+F62-F54 -> 568.31019 | G64: =+G62-G54 -> 719.06093 | H64: =+H62-H54 -> 779.05887 | I64: =+I62-I54 -> 0 | J64: =+J62-J54 -> 0 | K64: =+K62-K54 -> 0 | ... M64: =+M62-M54 -> 0
B66: Period | D66: =+C41 -> 0.5 | E66: =+D66+1 -> 1.5 | F66: =+E66+1 -> 2.5 | G66: =+F66+1 -> 3.5 | H66: =+G66+1 -> 4.5 | I66: =+H66+1 -> 5.5 | J66: =+I66+1 -> 6.5 | K66: =+J66+1 -> 7.5 | L66: =+K66+1 -> 8.5 | M66: =+L66+1 -> 9.5
B67: Discount factor | D67: =1/(1+$C$42)^D66 -> 0.96673649 | E67: =1/(1+$C$42)^E66 -> 0.90349205 | F67: =1/(1+$C$42)^F66 -> 0.84438509 | G67: =1/(1+$C$42)^G66 -> 0.78914494 | H67: =1/(1+$C$42)^H66 -> 0.73751864 | I67: =1/(1+$C$42)^I66 -> 0.68926976 | J67: =1/(1+$C$42)^J66 -> 0.64417734 | K67: =1/(1+$C$42)^K66 -> 0.6020349 | ... M67: =1/(1+$C$42)^M66 -> 0.5258406
B69: Discounted Excess earnings | D69: =+D64*D67 -> 528.72546 | E69: =+E64*E67 -> 545.73925 | F69: =+F64*F67 -> 479.87265 | G69: =+G64*G67 -> 567.44329 | H69: =+H64*H67 -> 574.57044 | I69: =+I64*I67 -> 0 | J69: =+J64*J67 -> 0 | K69: =+K64*K67 -> 0 | ... M69: =+M64*M67 -> 0
B71: Adjusted Capitale investito netto | C71: =+C52 -> 51971
B72: ∑ of Discounted Excess earnings | C72: =+SUM(D69:M69) -> 2696.3511
B73: Enterprise value | C73: =+SUM(C71:C72) -> 54667.351
B75: (+/-) Posizione finanziaria netta | C75: =+Proiezioni!E73 -> 60863
B76: (+/-) Partecipazioni | C76: =+Proiezioni!E75 -> -44567
B77: (+/-) Imposte differite | C77: =+Proiezioni!E77 -> -1832
B78: Bridge to Equity | C78: =+SUM(C75:C77) -> 14464
B80: Equity Value | C80: =+C73-C78 -> 40203.351
C83: Sensitivity analysis | Enterprise Value
F85: WACC
B86: LT g rate | C86: =+C73 -> 54667.351 | D86: 0.065 | E86: 0.07 | F86: 0.075
C87: 0.0125 | D87: 55863.016 | E87: 54667.351 | F87: 53498.193
C88: 0.015 | D88: 55863.016 | E88: 54667.351 | F88: 53498.193
C89: 0.0175 | D89: 55863.016 | E89: 54667.351 | F89: 53498.193
C92: Sensitivity analysis | Equity Value
F94: WACC
B95: LT g rate | C95: =+C80 -> 40203.351 | D95: 0.065 | E95: 0.07 | F95: 0.075
C96: 0.0125 | D96: 41399.016 | E96: 40203.351 | F96: 39034.193
C97: 0.015 | D97: 41399.016 | E97: 40203.351 | F97: 39034.193
C98: 0.0175 | D98: 41399.016 | E98: 40203.351 | F98: 39034.193

Sheet Multipli di transazioni
B3: Transacion multiples
B6: Transaction panel
B8: EUR/000 | C8: GAAP | D8: Deal date | E8: Purchase price | F8: Equity stake | G8: Implied equity value | H8: Posizione finanziaria netta | I8: Deal value | K8: EBITDA | L8: EBITDA multiple | N8: Y/N
B10: Deal 1 | C10: IFRS | D10: 2018 | E10: 57 | F10: 1 | G10: =+E10/F10 -> 57 | H10: 12 | I10: =+SUM(G10:H10) -> 69 | K10: 12.666661 | L10: =IF($N10="Y",I10/K10,"n.a.") -> 5.4473708 | N10: Y
B11: Deal 2 | C11: IFRS | D11: 2016 | E11: 124 | F11: 1 | G11: =+E11/F11 -> 124 | H11: 55 | I11: =+SUM(G11:H11) -> 179 | K11: 34.102549 | L11: =IF($N11="Y",I11/K11,"n.a.") -> 5.2488745 | N11: Y
B12: Deal 3 | C12: IFRS | D12: 2015 | E12: 250 | F12: 1 | G12: =+E12/F12 -> 250 | H12: -45 | I12: =+SUM(G12:H12) -> 205 | K12: 47.743569 | L12: =IF($N12="Y",I12/K12,"n.a.") -> 4.293772 | N12: Y
B13: Deal 4 | C13: IFRS | D13: 2012 | E13: 55 | F13: 0.75 | G13: =+E13/F13 -> 73.333333 | H13: -30 | I13: =+SUM(G13:H13) -> 43.333333 | K13: -20.46153 | L13: =IF($N13="Y",I13/K13,"n.a.") -> n.a. | N13: N
B14: Deal 5 | C14: IFRS | D14: 2019 | E14: 43 | F14: 0.51 | G14: =+E14/F14 -> 84.313725 | H14: 11 | I14: =+SUM(G14:H14) -> 95.313725 | K14: 20.46153 | L14: =IF($N14="Y",I14/K14,"n.a.") -> 4.6581916 | N14: Y
B15: Deal 6 | C15: ITA GAAP | D15: 2018 | E15: 78 | F15: 0.51 | G15: =+E15/F15 -> 152.94118 | H15: 27 | I15: =+SUM(G15:H15) -> 179.94118 | K15: 34.102549 | L15: =IF($N15="Y",I15/K15,"n.a.") -> 5.2764729 | N15: Y
B16: Deal 7 | C16: IFRS | D16: 2018 | E16: 92 | F16: 0.3 | G16: =+E16/F16 -> 306.66667 | H16: -5 | I16: =+SUM(G16:H16) -> 301.66667 | K16: 70.153816 | L16: =IF($N16="Y",I16/K16,"n.a.") -> 4.300075 | N16: Y
B17: Deal 8 | C17: IFRS | D17: 2017 | E17: 65 | F17: 1 | G17: =+E17/F17 -> 65 | H17: -2 | I17: =+SUM(G17:H17) -> 63 | K17: -8.769227 | L17: =IF($N17="Y",I17/K17,"n.a.") -> n.a. | N17: N
B18: Deal 9 | C18: IFRS | D18: 2016 | E18: 45 | F18: 0.8 | G18: =+E18/F18 -> 56.25 | H18: 55 | I18: =+SUM(G18:H18) -> 111.25 | K18: 0.97435855 | L18: =IF($N18="Y",I18/K18,"n.a.") -> n.a. | N18: N
B19: Deal 10 | C19: ITA GAAP | D19: 2014 | E19: 511 | F19: 0.95 | G19: =+E19/F19 -> 537.89474 | H19: 125 | I19: =+SUM(G19:H19) -> 662.89474 | K19: 140.30763 | L19: =IF($N19="Y",I19/K19,"n.a.") -> n.a. | N19: N
B20: Deal 11 | C20: ITA GAAP | D20: 2011 | E20: 450 | F20: 1 | G20: =+E20/F20 -> 450 | H20: 125 | I20: =+SUM(G20:H20) -> 575 | K20: 8.769227 | L20: =IF($N20="Y",I20/K20,"n.a.") -> n.a. | N20: N
B21: Deal 12 | C21: IFRS | D21: 2012 | E21: 200 | F21: 0.85 | G21: =+E21/F21 -> 235.29412 | H21: 46 | I21: =+SUM(G21:H21) -> 281.29412 | K21: 66.256381 | L21: =IF($N21="Y",I21/K21,"n.a.") -> n.a. | N21: N
... B24: Deal 15 | C24: ITA GAAP | D24: 2019 | E24: 55 | F24: 0.3 | G24: =+E24/F24 -> 183.33333 | H24: -25 | I24: =+SUM(G24:H24) -> 158.33333 | K24: 29.230757 | L24: =IF($N24="Y",I24/K24,"n.a.") -> 5.416669 | N24: Y
B25: Average | L25: =+AVERAGE(L10:L24) -> 4.9821317
B26: Median | L26: =+MEDIAN(L10:L24) -> 5.2322512
B27: 1st quartile | L27: =+QUARTILE(L10:L24,1) -> 4.5686625
B28: 3rd quartile | L28: =+QUARTILE(L10:L24,3) -> 5.3115219
N29: Source: MergerMarket
B30: Filters
B31: 1. EBITDA positivo
B32: 2. IFRS
B33: 3. Successivi a 2015
B36: Transaction multiple valuation
B38: EUR/000 | C38: Min | D38: Center | E38: Max
B40: EBITDA 2019 | C40: =+Proiezioni!$E$22 -> 11918 | D40: =+Proiezioni!$E$22 -> 11918 | E40: =+Proiezioni!$E$22 -> 11918
B41: EV/EBITDA | C41: =+L27 -> 4.5686625 | D41: =+L26 -> 5.2322512 | E41: =+L28 -> 5.3115219
B42: Enterprise Value | C42: =+C40*C41 -> 54449.319 | D42: =+D40*D41 -> 62357.969 | E42: =+E40*E41 -> 63302.718
B44: NWC adjustment | C44: 0 | D44: 0 | E44: 0
B45: altre PFN adjustments | C45: 0 | D45: 0 | E45: 0
B47: Adjusted Enterprise Value | C47: =+C42+SUM(C44:C45) -> 54449.319 | D47: =+D42+SUM(D44:D45) -> 62357.969 | E47: =+E42+SUM(E44:E45) -> 63302.718
B49: (+/-) Posizione finanziaria netta | C49: =+Proiezioni!$E$73 -> 60863 | D49: =+Proiezioni!$E$73 -> 60863 | E49: =+Proiezioni!$E$73 -> 60863
B50: (+/-) Partecipazioni | C50: =+Proiezioni!$E$75 -> -44567 | D50: =+Proiezioni!$E$75 -> -44567 | E50: =+Proiezioni!$E$75 -> -44567
B51: (+/-) Imposte differite | C51: =+Proiezioni!$E$77 -> -1832 | D51: =+Proiezioni!$E$77 -> -1832 | E51: =+Proiezioni!$E$77 -> -1832
B52: Bridge to Equity | C52: =+SUM(C49:C51) -> 14464 | D52: =+SUM(D49:D51) -> 14464 | E52: =+SUM(E49:E51) -> 14464
B54: Equity Value | C54: =+C47-C52 -> 39985.319 | D54: =+D47-D52 -> 47893.969 | E54: =+E47-E52 -> 48838.718

Sheet Multipli di borsa
B3: Peers panel
B6: Peers
B8: EUR/000 | C8: EV / EBITDA 2019 | D8: EV / EBITDA 2020
B10: Comp 1 | C10: 4.9116375 | D10: 4.1588096
B11: Comp 2 | C11: 6.8762925 | D11: 6.169928
B12: Comp 3 | C12: 7.85862 | D12: 6.4582988
B13: Comp 4 | C13: 4.4204738 | D13: 4.3199816
B14: Comp 5 | C14: 4.4204738 | D14: 4.0548644
B15: Comp 6 | C15: 4.2240083 | D15: 4.2126935
B16: Comp 7 | C16: 4.1257755 | D16: 3.5884799
B17: Comp 8 | C17: 3.4381463 | D17: 2.7257836
B18: Comp 9 | C18: 5.893965 | D18: 5.0542782
B19: Comp 10 | C19: 6.3851288 | D19: 6.0604898
B20: Comp 11 | C20: 8.8409475 | D20: 7.0557818
B21: Comp 12 | C21: 17.681895 | D21: 13.375326
... B24: Comp 15 | C24: 3.92931 | D24: 3.4423967
B25: Average | C25: =+AVERAGE(C10:C24) -> 6.286896 | D25: =+AVERAGE(D10:D24) -> 5.3877943
B26: Median | C26: =+MEDIAN(C10:C24) -> 5.4028013 | D26: =+MEDIAN(D10:D24) -> 4.9380278
B27: 1st quartile | C27: =+QUARTILE(C10:C24,1) -> 4.322241 | D27: =+QUARTILE(D10:D24,1) -> 4.106837
B28: 3rd quartile | C28: =+QUARTILE(C10:C24,3) -> 6.6307106 | D28: =+QUARTILE(D10:D24,3) -> 6.1152089
B31: EUR/000 | C31: 2019 | D31: 2020
B33: EBITDA 2019 | C33: =+Proiezioni!E22 -> 11918 | D33: =+Proiezioni!F22 -> 12100
B34: EV/EBITDA | C34: =+C26 -> 5.4028013 | D34: =+D26 -> 4.9380278
B35: Enterprise Value | C35: =+C33*C34 -> 64390.585 | D35: =+D33*D34 -> 59750.136
B37: NWC adjustment | C37: 0 | D37: 0
B38: altre PFN adjustments | C38: 0 | D38: 0
B40: Adjusted Enterprise Value | C40: =+C35+SUM(C37:C38) -> 64390.585 | D40: =+D35+SUM(D37:D38) -> 59750.136
B42: (+/-) Posizione finanziaria netta | C42: =+Proiezioni!$E$73 -> 60863 | D42: =+Proiezioni!$E$73 -> 60863
B43: (+/-) Partecipazioni | C43: =+Proiezioni!$E$75 -> -44567 | D43: =+Proiezioni!$E$75 -> -44567
B44: (+/-) Imposte differite | C44: =+Proiezioni!$E$77 -> -1832 | D44: =+Proiezioni!$E$77 -> -1832
B45: Bridge to Equity | C45: =+SUM(C42:C44) -> 14464 | D45: =+SUM(D42:D44) -> 14464
B47: Equity Value | C47: =+C40-C45 -> 49926.585 | D47: =+D40-D45 -> 45286.136

Sheet Proiezioni
B3: Proiezioni
B6: Profit & Loss
B8: EUR/000 | C8: =+'Actual data'!G8 -> 2017 | D8: =+C8+1 -> 2018 | E8: =+D8+1 -> 2019 | F8: =+E8+1 -> 2020 | G8: =+F8+1 -> 2021 | H8: =+G8+1 -> 2022 | I8: =+H8+1 -> 2023 | J8: =+I8+1 -> 2024
B10: Ricavi | C10: =+'Actual data'!G10 -> 29488 | D10: =+'Actual data'!H10 -> 31352 | E10: =+'Actual data'!I10 -> 32326 | F10: 33000 | G10: 33500 | H10: 33750 | I10: 34500 | J10: 34750
B11: Altri ricavi | C11: =+'Actual data'!G11 -> 126 | D11: =+'Actual data'!H11 -> 0 | E11: =+'Actual data'!I11 -> 48 | F11: 0 | G11: 0 | H11: 0 | I11: 0 | J11: 0
B12: Valore della produzione | C12: =+SUM(C10:C11) -> 29614 | D12: =+SUM(D10:D11) -> 31352 | E12: =+SUM(E10:E11) -> 32374 | F12: =+SUM(F10:F11) -> 33000 | G12: =+SUM(G10:G11) -> 33500 | H12: =+SUM(H10:H11) -> 33750 | I12: =+SUM(I10:I11) -> 34500 | J12: =+SUM(J10:J11) -> 34750
B13: YoY Delta | C13: =+IFERROR(C12/#REF!-1,"n.a.") -> n.a. | D13: =+IFERROR(D12/C12-1,"n.a.") -> 0.058688458 | E13: =+IFERROR(E12/D12-1,"n.a.") -> 0.032597601 | F13: =+IFERROR(F12/E12-1,"n.a.") -> 0.019336505 | G13: =+IFERROR(G12/F12-1,"n.a.") -> 0.015151515 | H13: =+IFERROR(H12/G12-1,"n.a.") -> 0.0074626866 | I13: =+IFERROR(I12/H12-1,"n.a.") -> 0.022222222 | J13: =+IFERROR(J12/I12-1,"n.a.") -> 0.0072463768
B15: Costo delle materie prime | C15: =+'Actual data'!G15 -> -710 | D15: =+'Actual data'!H15 -> -775 | E15: =+'Actual data'!I15 -> -882 | F15: -900 | G15: -910 | H15: -920 | I15: -930 | J15: -940
B16: Variazione materie prime | C16: =+'Actual data'!G16 -> 0 | D16: =+'Actual data'!H16 -> 0 | E16: =+'Actual data'!I16 -> 0 | F16: 0 | G16: 0 | I16: 0 | J16: 0
B17: Costi per servizi | C17: =+'Actual data'!G17 -> -9650 | D17: =+'Actual data'!H17 -> -11396 | E17: =+'Actual data'!I17 -> -11688 | F17: -12600 | G17: -12800 | H17: -12900 | I17: -13100 | J17: -13150
B18: Costo del personale | C18: =+'Actual data'!G18 -> -5041 | D18: =+'Actual data'!H18 -> -5577 | E18: =+'Actual data'!I18 -> -6083 | F18: -5600 | G18: -5600 | H18: -5650 | I18: -5675 | J18: -5700
B19: Oneri diversi di gestione | C19: =+'Actual data'!G19 -> -1989 | D19: =+'Actual data'!H19 -> -1665 | E19: =+'Actual data'!I19 -> -1803 | F19: -1800 | G19: -1800 | H19: -1800 | I19: -1800 | J19: -1800
B20: Costi operativi | C20: =+SUM(C15:C19) -> -17390 | D20: =+SUM(D15:D19) -> -19413 | E20: =+SUM(E15:E19) -> -20456 | F20: =+SUM(F15:F19) -> -20900 | G20: =+SUM(G15:G19) -> -21110 | H20: =+SUM(H15:H19) -> -21270 | I20: =+SUM(I15:I19) -> -21505 | J20: =+SUM(J15:J19) -> -21590
B22: EBITDA | C22: =+C12+C20 -> 12224 | D22: =+D12+D20 -> 11939 | E22: =+E12+E20 -> 11918 | F22: =+F12+F20 -> 12100 | G22: =+G12+G20 -> 12390 | H22: =+H12+H20 -> 12480 | I22: =+I12+I20 -> 12995 | J22: =+J12+J20 -> 13160
B23: % Ricavi | C23: =+C22/C$12 -> 0.41277774 | D23: =+D22/D$12 -> 0.38080505 | E23: =+E22/E$12 -> 0.36813492 | F23: =+F22/F$12 -> 0.36666667 | G23: =+G22/G$12 -> 0.36985075 | H23: =+H22/H$12 -> 0.36977778 | I23: =+I22/I$12 -> 0.37666667 | J23: =+J22/J$12 -> 0.37870504
B25: D&A | C25: =+'Actual data'!G25 -> -6532 | D25: =+'Actual data'!H25 -> -6034 | E25: =+'Actual data'!I25 -> -6193 | F25: -6250 | G25: -6400 | H25: -6500 | I25: -6550 | J25: -6600
B26: Accantonamenti | C26: =+'Actual data'!G26 -> -60 | D26: =+'Actual data'!H26 -> 0 | E26: =+'Actual data'!I26 -> 0 | F26: 0 | G26: 0 | H26: 0 | I26: 0 | J26: 0
B28: EBIT | C28: =+C22+SUM(C25:C26) -> 5632 | D28: =+D22+SUM(D25:D26) -> 5905 | E28: =+E22+SUM(E25:E26) -> 5725 | F28: =+F22+SUM(F25:F26) -> 5850 | G28: =+G22+SUM(G25:G26) -> 5990 | H28: =+H22+SUM(H25:H26) -> 5980 | I28: =+I22+SUM(I25:I26) -> 6445 | J28: =+J22+SUM(J25:J26) -> 6560
B29: % Ricavi | C29: =+C28/C$12 -> 0.19018032 | D29: =+D28/D$12 -> 0.18834524 | E29: =+E28/E$12 -> 0.17683944 | F29: =+F28/F$12 -> 0.17727273 | G29: =+G28/G$12 -> 0.17880597 | H29: =+H28/H$12 -> 0.17718519 | I29: =+I28/I$12 -> 0.18681159 | J29: =+J28/J$12 -> 0.18877698
B31: Impairment of assets | C31: =+'Actual data'!G31 -> 0 | D31: =+'Actual data'!H31 -> -236 | E31: =+'Actual data'!I31 -> -56 | F31: 0 | G31: 0 | H31: 0 | I31: 0 | J31: 0
B32: Proventi/(oneri) finanziari | C32: =+'Actual data'!G32 -> -1257 | D32: =+'Actual data'!H32 -> -1393 | E32: =+'Actual data'!I32 -> -1619 | F32: -1619 | G32: -1619 | H32: -1619 | I32: -1619 | J32: -1619
B33: Costi straordinari | C33: =+'Actual data'!G33 -> 129 | D33: =+'Actual data'!H33 -> 106 | E33: =+'Actual data'!I33 -> -66 | F33: 0 | G33: 0 | H33: 0 | I33: 0 | J33: 0
B35: EBT | C35: =+C28+SUM(C31:C33) -> 4504 | D35: =+D28+SUM(D31:D33) -> 4382 | E35: =+E28+SUM(E31:E33) -> 3984 | F35: =+F28+SUM(F31:F33) -> 4231 | G35: =+G28+SUM(G31:G33) -> 4371 | H35: =+H28+SUM(H31:H33) -> 4361 | I35: =+I28+SUM(I31:I33) -> 4826 | J35: =+J28+SUM(J31:J33) -> 4941
B37: Imposte | C37: =+'Actual data'!G37 -> -508 | D37: =+'Actual data'!H37 -> -591 | E37: =+'Actual data'!I37 -> 0 | F37: -1040.949 | G37: -1080.009 | H37: -1077.219 | I37: -1206.954 | J37: -1239.039
B39: Net result | C39: =+C35+C37 -> 3996 | D39: =+D35+D37 -> 3791 | E39: =+E35+E37 -> 3984 | F39: =+F35+F37 -> 3190.051 | G39: =+G35+G37 -> 3290.991 | H39: =+H35+H37 -> 3283.781 | I39: =+I35+I37 -> 3619.046 | J39: =+J35+J37 -> 3701.961
B40: Check
B43: Balance sheet
B45: EUR/000 | C45: =+C$8 -> 2017 | D45: =+D$8 -> 2018 | E45: =+E$8 -> 2019 | F45: =+F$8 -> 2020 | G45: =+G$8 -> 2021 | H45: =+H$8 -> 2022 | I45: =+I$8 -> 2023 | J45: =+J$8 -> 2024
B47: Intangible assets | C47: =+'Actual data'!G47 -> 17 | D47: =+'Actual data'!H47 -> 13 | E47: =+'Actual data'!I47 -> 3 | F47: 3 | G47: 3 | H47: 3 | I47: 3 | J47: 3
B48: Goodwill | C48: =+'Actual data'!G48 -> 3821 | D48: =+'Actual data'!H48 -> 3821 | E48: =+'Actual data'!I48 -> 3821 | F48: 3821 | G48: 3821 | H48: 3821 | I48: 3821 | J48: 3821
B49: Tangible assets | C49: =+'Actual data'!G49 -> 31257 | D49: =+'Actual data'!H49 -> 31453 | E49: =+'Actual data'!I49 -> 35954 | F49: 36704 | G49: 37304 | H49: 37804 | I49: 40254 | J49: 40654
B50: Attivo fisso | C50: =+SUM(C47:C49) -> 35095 | D50: =+SUM(D47:D49) -> 35287 | E50: =+SUM(E47:E49) -> 39778 | F50: =+SUM(F47:F49) -> 40528 | G50: =+SUM(G47:G49) -> 41128 | H50: =+SUM(H47:H49) -> 41628 | I50: =+SUM(I47:I49) -> 44078 | J50: =+SUM(J47:J49) -> 44478
B52: RImanenze | C52: =+'Actual data'!G52 -> 142 | D52: =+'Actual data'!H52 -> 103 | E52: =+'Actual data'!I52 -> 140 | F52: 140 | G52: 140 | H52: 140 | I52: 140 | J52: 140
B53: Crediti commerciali | C53: =+'Actual data'!G53 -> 14732 | D53: =+'Actual data'!H53 -> 13653 | E53: =+'Actual data'!I53 -> 17104 | F53: 17434.732 | G53: 17698.894 | H53: 17830.975 | I53: 18227.219 | J53: 18359.301
B54: Debiti commerciali | C54: =+'Actual data'!G54 -> -6003 | D54: =+'Actual data'!H54 -> -7598 | E54: =+'Actual data'!I54 -> -6246 | F54: -6648.8416 | G54: -6740.1002 | H54: -6787.9023 | I54: -6879.1609 | J54: -6905.2348
B55: Intercompany accounts | C55: =+'Actual data'!G55 -> 1658 | D55: =+'Actual data'!H55 -> 1223 | E55: =+'Actual data'!I55 -> 4159 | F55: 4239.4205 | G55: 4303.6542 | H55: 4335.771 | I55: 4432.1215 | J55: 4464.2383
B56: Altre attività/passività correnti | C56: =+'Actual data'!G56 -> -4538 | D56: =+'Actual data'!H56 -> -3387 | E56: =+'Actual data'!I56 -> -4004 | F56: -4004 | G56: -4004 | H56: -4004 | I56: -4004 | J56: -4004
B57: Capitale circolante netto | C57: =+SUM(C52:C56) -> 5991 | D57: =+SUM(D52:D56) -> 3994 | E57: =+SUM(E52:E56) -> 11153 | F57: =+SUM(F52:F56) -> 11161.311 | G57: =+SUM(G52:G56) -> 11398.448 | H57: =+SUM(H52:H56) -> 11514.844 | I57: =+SUM(I52:I56) -> 11916.18 | J57: =+SUM(J52:J56) -> 12054.304
B59: Attività/passività non correnti | C59: =+'Actual data'!G59 -> 11 | D59: =+'Actual data'!H59 -> 11 | E59: =+'Actual data'!I59 -> 11 | F59: 11 | G59: 11 | H59: 11 | I59: 11 | J59: 11
B61: Fondi | C61: =+'Actual data'!G61 -> -18 | D61: =+'Actual data'!H61 -> -18 | E61: =+'Actual data'!I61 -> -17 | F61: -17 | G61: -17 | H61: -17 | I61: -17 | J61: -17
B63: Capitale investito netto | C63: =+C50+C57+C59+C61 -> 41079 | D63: =+D50+D57+D59+D61 -> 39274 | E63: =+E50+E57+E59+E61 -> 50925 | F63: =+F50+F57+F59+F61 -> 51683.311 | G63: =+G50+G57+G59+G61 -> 52520.448 | H63: =+H50+H57+H59+H61 -> 53136.844 | I63: =+I50+I57+I59+I61 -> 55988.18 | J63: =+J50+J57+J59+J61 -> 56526.304
B65: Patrimonio netto | C65: =-SUMIFS(Mapping!G$5:G$106,Mapping!$J$5:$J$106,Proiezioni!$B65)/1000+SUMIFS(Mapping!G$110:G$191,Mapping!$J$110:$J$191,Proiezioni!$B65)/1000 -> 28757 | D65: =-SUMIFS(Mapping!H$5:H$106,Mapping!$J$5:$J$106,Proiezioni!$B65)/1000+SUMIFS(Mapping!H$110:H$191,Mapping!$J$110:$J$191,Proiezioni!$B65)/1000 -> 32528 | E65: =-SUMIFS(Mapping!I$5:I$106,Mapping!$J$5:$J$106,Proiezioni!$B65)/1000+SUMIFS(Mapping!I$110:I$191,Mapping!$J$110:$J$191,Proiezioni!$B65)/1000 -> 36461 | F65: 39151.051 | G65: 41942.042 | H65: 44725.823 | I65: 47844.869 | J65: 51046.83
B67: Passività finanziarie | C67: =+'Actual data'!G67 -> 23579 | D67: =+'Actual data'!H67 -> 18189 | E67: =+'Actual data'!I67 -> 14006 | F67: 14006 | G67: 14006 | H67: 14006 | I67: 14006 | J67: 14006
B68: Passività finanziarie - IC | C68: =+'Actual data'!G68 -> 30205 | D68: =+'Actual data'!H68 -> 50215 | E68: =+'Actual data'!I68 -> 68813 | F68: 68813 | G68: 68813 | H68: 68813 | I68: 68813 | J68: 68813
B69: TFR | C69: =+'Actual data'!G69 -> 1152 | D69: =+'Actual data'!H69 -> 1082 | E69: =+'Actual data'!I69 -> 1310 | F69: 1310 | G69: 1310 | H69: 1310 | I69: 1310 | J69: 1310
B70: Attività finanziarie | C70: =+'Actual data'!G70 -> -2044 | D70: =+'Actual data'!H70 -> -19331 | E70: =+'Actual data'!I70 -> -23165 | F70: -23165 | G70: -23165 | H70: -23165 | I70: -23165 | J70: -23165
B71: Attività finanziarie - IC | C71: =+'Actual data'!G71 -> -136 | D71: =+'Actual data'!H71 -> -281 | E71: =+'Actual data'!I71 -> 0 | F71: 0 | G71: 0 | H71: 0 | I71: 0 | J71: 0
B72: Cash and cash equivalents | C72: =+'Actual data'!G72 -> -337 | D72: =+'Actual data'!H72 -> -205 | E72: =+'Actual data'!I72 -> -101 | F72: -2032.7405 | G72: -3986.5938 | H72: -6153.9789 | I72: -6421.6891 | J72: -9085.5259
B73: Posizione finanziaria netta | C73: =+SUM(C67:C72) -> 52419 | D73: =+SUM(D67:D72) -> 49669 | E73: =+SUM(E67:E72) -> 60863 | F73: =+SUM(F67:F72) -> 58931.26 | G73: =+SUM(G67:G72) -> 56977.406 | H73: =+SUM(H67:H72) -> 54810.021 | I73: =+SUM(I67:I72) -> 54542.311 | J73: =+SUM(J67:J72) -> 51878.474
B75: Partecipazioni | C75: =+'Actual data'!G75 -> -38484 | D75: =+'Actual data'!H75 -> -41017 | E75: =+'Actual data'!I75 -> -44567 | F75: -44567 | G75: -44567 | H75: -44567 | I75: -44567 | J75: -44567
B77: Imposte differite | C77: =+'Actual data'!G77 -> -1613 | D77: =+'Actual data'!H77 -> -1906 | E77: =+'Actual data'!I77 -> -1832 | F77: -1832 | G77: -1832 | H77: -1832 | I77: -1832 | J77: -1832
B79: Fonti di finanziamento | C79: =+C65+C73+C75+C77 -> 41079 | D79: =+D65+D73+D75+D77 -> 39274 | E79: =+E65+E73+E75+E77 -> 50925 | F79: =+F65+F73+F75+F77 -> 51683.311 | G79: =+G65+G73+G75+G77 -> 52520.448 | H79: =+H65+H73+H75+H77 -> 53136.844 | I79: =+I65+I73+I75+I77 -> 55988.18 | J79: =+J65+J73+J75+J77 -> 56526.304
B80: Check | C80: =+C79-C63 -> 0 | D80: =+D79-D63 -> 0 | E80: =+E79-E63 -> 0 | F80: =+F79-F63 -> 0 | G80: =+G79-G63 -> 0 | H80: =+H79-H63 -> 0 | I80: =+I79-I63 -> 0 | J80: =+J79-J63 -> 0
B83: Cash flow statement
B85: EUR/000 | C85: =+C$8 -> 2017 | D85: =+D$8 -> 2018 | E85: =+E$8 -> 2019 | F85: =+F$8 -> 2020 | G85: =+G$8 -> 2021 | H85: =+H$8 -> 2022 | I85: =+I$8 -> 2023 | J85: =+J$8 -> 2024
B87: EBITDA | D87: =+D22 -> 11939 | E87: =+E22 -> 11918 | F87: =+F22 -> 12100 | G87: =+G22 -> 12390 | H87: =+H22 -> 12480 | I87: =+I22 -> 12995 | J87: =+J22 -> 13160
B89: Delta in NWC | D89: =+C57-D57 -> 1997 | E89: =+D57-E57 -> -7159 | F89: =+E57-F57 -> -8.3105194 | G89: =+F57-G57 -> -237.13763 | H89: =+G57-H57 -> -116.39599 | I89: =+H57-I57 -> -401.33576 | J89: =+I57-J57 -> -138.12423
B90: Capex | D90: =+C50-D50+D25 -> -6226 | E90: =+D50-E50+E25 -> -10684 | F90: =+E50-F50+F25 -> -7000 | G90: =+F50-G50+G25 -> -7000 | H90: =+G50-H50+H25 -> -7000 | I90: =+H50-I50+I25 -> -9000 | J90: =+I50-J50+J25 -> -7000
B91: Delta in altre attività/passività | D91: =+C59-D59 -> 0 | E91: =+D59-E59 -> 0 | F91: =+E59-F59 -> 0 | G91: =+F59-G59 -> 0 | H91: =+G59-H59 -> 0 | I91: =+H59-I59 -> 0 | J91: =+I59-J59 -> 0
B92: Fondi | D92: =+C61-D61+D26 -> 0 | E92: =+D61-E61+E26 -> -1 | F92: =+E61-F61+F26 -> 0 | G92: =+F61-G61+G26 -> 0 | H92: =+G61-H61+H26 -> 0 | I92: =+H61-I61+I26 -> 0 | J92: =+I61-J61+J26 -> 0
B93: Taxation | D93: =+D37+D77-C77 -> -884 | E93: =+E37+E77-D77 -> 74 | F93: =+F37+F77-E77 -> -1040.949 | G93: =+G37+G77-F77 -> -1080.009 | H93: =+H37+H77-G77 -> -1077.219 | I93: =+I37+I77-H77 -> -1206.954 | J93: =+J37+J77-I77 -> -1239.039
B94: Costi straordinari | D94: =+D33 -> 106 | E94: =+E33 -> -66 | F94: =+F33 -> 0 | G94: =+G33 -> 0 | H94: =+H33 -> 0 | I94: =+I33 -> 0 | J94: =+J33 -> 0
B96: Operating cash flow | D96: =+D87+SUM(D89:D94) -> 6932 | E96: =+E87+SUM(E89:E94) -> -5918 | F96: =+F87+SUM(F89:F94) -> 4050.7405 | G96: =+G87+SUM(G89:G94) -> 4072.8534 | H96: =+H87+SUM(H89:H94) -> 4286.385 | I96: =+I87+SUM(I89:I94) -> 2386.7102 | J96: =+J87+SUM(J89:J94) -> 4782.8368
B98: Proventi/(oneri) finanziari | D98: =+D32 -> -1393 | E98: =+E32 -> -1619 | F98: =+F32 -> -1619 | G98: =+G32 -> -1619 | H98: =+H32 -> -1619 | I98: =+I32 -> -1619 | J98: =+J32 -> -1619
B99: Delta in financial attività/passività | D99: =+SUM(D67:D71)-SUM(C67:C71)+D31 -> -3118 | E99: =+SUM(E67:E71)-SUM(D67:D71)+E31 -> 11034 | F99: =+SUM(F67:F71)-SUM(E67:E71)+F31 -> 0 | G99: =+SUM(G67:G71)-SUM(F67:F71)+G31 -> 0 | H99: =+SUM(H67:H71)-SUM(G67:G71)+H31 -> 0 | I99: =+SUM(I67:I71)-SUM(H67:H71)+I31 -> 0 | J99: =+SUM(J67:J71)-SUM(I67:I71)+J31 -> 0
B100: Delta in Partecipazioni | D100: =+D75-C75 -> -2533 | E100: =+E75-D75 -> -3550 | F100: =+F75-E75 -> 0 | G100: =+G75-F75 -> 0 | H100: =+H75-G75 -> 0 | I100: =+I75-H75 -> 0 | J100: =+J75-I75 -> 0
B101: Equity movements | D101: =+D65-C65-D39 -> -20 | E101: =+E65-D65-E39 -> -51 | F101: =+F65-E65-F39 -> -500 | G101: =+G65-F65-G39 -> -500 | H101: =+H65-G65-H39 -> -500 | I101: =+I65-H65-I39 -> -500 | J101: =+J65-I65-J39 -> -500
B103: Financing | D103: =+SUM(D98:D101) -> -7064 | E103: =+SUM(E98:E101) -> 5814 | F103: =+SUM(F98:F101) -> -2119 | G103: =+SUM(G98:G101) -> -2119 | H103: =+SUM(H98:H101) -> -2119 | I103: =+SUM(I98:I101) -> -2119 | J103: =+SUM(J98:J101) -> -2119
B105: Delta in cash and cash equivalents | D105: =+D96+D103 -> -132 | E105: =+E96+E103 -> -104 | F105: =+F96+F103 -> 1931.7405 | G105: =+G96+G103 -> 1953.8534 | H105: =+H96+H103 -> 2167.385 | I105: =+I96+I103 -> 267.71024 | J105: =+J96+J103 -> 2663.8368
B106: Check | D106: =+D72-C72+D105 -> 0 | E106: =+E72-D72+E105 -> 0 | F106: =+F72-E72+F105 -> 0 | G106: =+G72-F72+G105 -> 1.8189894e-12 | H106: =+H72-G72+H105 -> 0 | I106: =+I72-H72+I105 -> 2.2737368e-12 | J106: =+J72-I72+J105 -> 0

Sheet Actual data
B3: Actual data
B6: Profit & Loss
B8: EUR/000 | C8: 2013 | D8: =+C8+1 -> 2014 | E8: =+D8+1 -> 2015 | F8: =+E8+1 -> 2016 | G8: =+F8+1 -> 2017 | H8: =+G8+1 -> 2018 | I8: =+H8+1 -> 2019
B10: Ricavi | C10: =+SUMIFS(Mapping!C$201:C$289,Mapping!$J$201:$J$289,'Actual data'!$B10)/1000 -> 28776 | D10: =+SUMIFS(Mapping!D$201:D$289,Mapping!$J$201:$J$289,'Actual data'!$B10)/1000 -> 29846 | E10: =+SUMIFS(Mapping!E$201:E$289,Mapping!$J$201:$J$289,'Actual data'!$B10)/1000 -> 29619 | F10: =+SUMIFS(Mapping!F$201:F$289,Mapping!$J$201:$J$289,'Actual data'!$B10)/1000 -> 27209 | G10: =+SUMIFS(Mapping!G$201:G$289,Mapping!$J$201:$J$289,'Actual data'!$B10)/1000 -> 29488 | H10: =+SUMIFS(Mapping!H$201:H$289,Mapping!$J$201:$J$289,'Actual data'!$B10)/1000 -> 31352 | I10: =+SUMIFS(Mapping!I$201:I$289,Mapping!$J$201:$J$289,'Actual data'!$B10)/1000 -> 32326
B11: Altri ricavi | C11: =+SUMIFS(Mapping!C$201:C$289,Mapping!$J$201:$J$289,'Actual data'!$B11)/1000 -> 97 | D11: =+SUMIFS(Mapping!D$201:D$289,Mapping!$J$201:$J$289,'Actual data'!$B11)/1000 -> 120 | E11: =+SUMIFS(Mapping!E$201:E$289,Mapping!$J$201:$J$289,'Actual data'!$B11)/1000 -> 114 | F11: =+SUMIFS(Mapping!F$201:F$289,Mapping!$J$201:$J$289,'Actual data'!$B11)/1000 -> 1325 | G11: =+SUMIFS(Mapping!G$201:G$289,Mapping!$J$201:$J$289,'Actual data'!$B11)/1000 -> 126 | H11: =+SUMIFS(Mapping!H$201:H$289,Mapping!$J$201:$J$289,'Actual data'!$B11)/1000 -> 0 | I11: =+SUMIFS(Mapping!I$201:I$289,Mapping!$J$201:$J$289,'Actual data'!$B11)/1000 -> 48
B12: Valore della produzione | C12: =+SUM(C10:C11) -> 28873 | D12: =+SUM(D10:D11) -> 29966 | E12: =+SUM(E10:E11) -> 29733 | F12: =+SUM(F10:F11) -> 28534 | G12: =+SUM(G10:G11) -> 29614 | H12: =+SUM(H10:H11) -> 31352 | I12: =+SUM(I10:I11) -> 32374
B13: YoY Delta | C13: =+IFERROR(C12/B12-1,"n.a.") -> n.a. | D13: =+IFERROR(D12/C12-1,"n.a.") -> 0.037855436 | E13: =+IFERROR(E12/D12-1,"n.a.") -> -0.0077754789 | F13: =+IFERROR(F12/E12-1,"n.a.") -> -0.040325564 | G13: =+IFERROR(G12/F12-1,"n.a.") -> 0.037849583 | H13: =+IFERROR(H12/G12-1,"n.a.") -> 0.058688458 | I13: =+IFERROR(I12/H12-1,"n.a.") -> 0.032597601
B15: Costo delle materie prime | C15: =-SUMIFS(Mapping!C$201:C$289,Mapping!$J$201:$J$289,'Actual data'!$B15)/1000 -> -2623 | D15: =-SUMIFS(Mapping!D$201:D$289,Mapping!$J$201:$J$289,'Actual data'!$B15)/1000 -> -2548 | E15: =-SUMIFS(Mapping!E$201:E$289,Mapping!$J$201:$J$289,'Actual data'!$B15)/1000 -> -1798 | F15: =-SUMIFS(Mapping!F$201:F$289,Mapping!$J$201:$J$289,'Actual data'!$B15)/1000 -> -1029 | G15: =-SUMIFS(Mapping!G$201:G$289,Mapping!$J$201:$J$289,'Actual data'!$B15)/1000 -> -710 | H15: =-SUMIFS(Mapping!H$201:H$289,Mapping!$J$201:$J$289,'Actual data'!$B15)/1000 -> -775 | I15: =-SUMIFS(Mapping!I$201:I$289,Mapping!$J$201:$J$289,'Actual data'!$B15)/1000 -> -882
B16: Variazione materie prime | C16: =-SUMIFS(Mapping!C$201:C$289,Mapping!$J$201:$J$289,'Actual data'!$B16)/1000 -> 0 | D16: =-SUMIFS(Mapping!D$201:D$289,Mapping!$J$201:$J$289,'Actual data'!$B16)/1000 -> 0 | E16: =-SUMIFS(Mapping!E$201:E$289,Mapping!$J$201:$J$289,'Actual data'!$B16)/1000 -> 0 | F16: =-SUMIFS(Mapping!F$201:F$289,Mapping!$J$201:$J$289,'Actual data'!$B16)/1000 -> 0 | G16: =-SUMIFS(Mapping!G$201:G$289,Mapping!$J$201:$J$289,'Actual data'!$B16)/1000 -> 0 | H16: =-SUMIFS(Mapping!H$201:H$289,Mapping!$J$201:$J$289,'Actual data'!$B16)/1000 -> 0 | I16: =-SUMIFS(Mapping!I$201:I$289,Mapping!$J$201:$J$289,'Actual data'!$B16)/1000 -> 0
B17: Costi per servizi | C17: =-SUMIFS(Mapping!C$201:C$289,Mapping!$J$201:$J$289,'Actual data'!$B17)/1000 -> -9218 | D17: =-SUMIFS(Mapping!D$201:D$289,Mapping!$J$201:$J$289,'Actual data'!$B17)/1000 -> -9743 | E17: =-SUMIFS(Mapping!E$201:E$289,Mapping!$J$201:$J$289,'Actual data'!$B17)/1000 -> -10257 | F17: =-SUMIFS(Mapping!F$201:F$289,Mapping!$J$201:$J$289,'Actual data'!$B17)/1000 -> -12226 | G17: =-SUMIFS(Mapping!G$201:G$289,Mapping!$J$201:$J$289,'Actual data'!$B17)/1000 -> -9650 | H17: =-SUMIFS(Mapping!H$201:H$289,Mapping!$J$201:$J$289,'Actual data'!$B17)/1000 -> -11396 | I17: =-SUMIFS(Mapping!I$201:I$289,Mapping!$J$201:$J$289,'Actual data'!$B17)/1000 -> -11688
B18: Costo del personale | C18: =-SUMIFS(Mapping!C$201:C$289,Mapping!$J$201:$J$289,'Actual data'!$B18)/1000 -> -5086 | D18: =-SUMIFS(Mapping!D$201:D$289,Mapping!$J$201:$J$289,'Actual data'!$B18)/1000 -> -5072 | E18: =-SUMIFS(Mapping!E$201:E$289,Mapping!$J$201:$J$289,'Actual data'!$B18)/1000 -> -4727 | F18: =-SUMIFS(Mapping!F$201:F$289,Mapping!$J$201:$J$289,'Actual data'!$B18)/1000 -> -4714 | G18: =-SUMIFS(Mapping!G$201:G$289,Mapping!$J$201:$J$289,'Actual data'!$B18)/1000 -> -5041 | H18: =-SUMIFS(Mapping!H$201:H$289,Mapping!$J$201:$J$289,'Actual data'!$B18)/1000 -> -5577 | I18: =-SUMIFS(Mapping!I$201:I$289,Mapping!$J$201:$J$289,'Actual data'!$B18)/1000 -> -6083
B19: Oneri diversi di gestione | C19: =-SUMIFS(Mapping!C$201:C$289,Mapping!$J$201:$J$289,'Actual data'!$B19)/1000 -> -1800 | D19: =-SUMIFS(Mapping!D$201:D$289,Mapping!$J$201:$J$289,'Actual data'!$B19)/1000 -> -1732 | E19: =-SUMIFS(Mapping!E$201:E$289,Mapping!$J$201:$J$289,'Actual data'!$B19)/1000 -> -1674 | F19: =-SUMIFS(Mapping!F$201:F$289,Mapping!$J$201:$J$289,'Actual data'!$B19)/1000 -> -1719 | G19: =-SUMIFS(Mapping!G$201:G$289,Mapping!$J$201:$J$289,'Actual data'!$B19)/1000 -> -1989 | H19: =-SUMIFS(Mapping!H$201:H$289,Mapping!$J$201:$J$289,'Actual data'!$B19)/1000 -> -1665 | I19: =-SUMIFS(Mapping!I$201:I$289,Mapping!$J$201:$J$289,'Actual data'!$B19)/1000 -> -1803
B20: Costi operativi | C20: =+SUM(C15:C19) -> -18727 | D20: =+SUM(D15:D19) -> -19095 | E20: =+SUM(E15:E19) -> -18456 | F20: =+SUM(F15:F19) -> -19688 | G20: =+SUM(G15:G19) -> -17390 | H20: =+SUM(H15:H19) -> -19413 | I20: =+SUM(I15:I19) -> -20456
B22: EBITDA | C22: =+C12+C20 -> 10146 | D22: =+D12+D20 -> 10871 | E22: =+E12+E20 -> 11277 | F22: =+F12+F20 -> 8846 | G22: =+G12+G20 -> 12224 | H22: =+H12+H20 -> 11939 | I22: =+I12+I20 -> 11918
B23: % Ricavi | C23: =+C22/C$12 -> 0.35140096 | D23: =+D22/D$12 -> 0.36277781 | E23: =+E22/E$12 -> 0.37927555 | F23: =+F22/F$12 -> 0.31001612 | G23: =+G22/G$12 -> 0.41277774 | H23: =+H22/H$12 -> 0.38080505 | I23: =+I22/I$12 -> 0.36813492
B25: D&A | C25: =-SUMIFS(Mapping!C$201:C$289,Mapping!$J$201:$J$289,'Actual data'!$B25)/1000 -> -4849 | D25: =-SUMIFS(Mapping!D$201:D$289,Mapping!$J$201:$J$289,'Actual data'!$B25)/1000 -> -5193 | E25: =-SUMIFS(Mapping!E$201:E$289,Mapping!$J$201:$J$289,'Actual data'!$B25)/1000 -> -5295 | F25: =-SUMIFS(Mapping!F$201:F$289,Mapping!$J$201:$J$289,'Actual data'!$B25)/1000 -> -5017 | G25: =-SUMIFS(Mapping!G$201:G$289,Mapping!$J$201:$J$289,'Actual data'!$B25)/1000 -> -6532 | H25: =-SUMIFS(Mapping!H$201:H$289,Mapping!$J$201:$J$289,'Actual data'!$B25)/1000 -> -6034 | I25: =-SUMIFS(Mapping!I$201:I$289,Mapping!$J$201:$J$289,'Actual data'!$B25)/1000 -> -6193
B26: Accantonamenti | C26: =-SUMIFS(Mapping!C$201:C$289,Mapping!$J$201:$J$289,'Actual data'!$B26)/1000 -> -767 | D26: =-SUMIFS(Mapping!D$201:D$289,Mapping!$J$201:$J$289,'Actual data'!$B26)/1000 -> -468 | E26: =-SUMIFS(Mapping!E$201:E$289,Mapping!$J$201:$J$289,'Actual data'!$B26)/1000 -> -353 | F26: =-SUMIFS(Mapping!F$201:F$289,Mapping!$J$201:$J$289,'Actual data'!$B26)/1000 -> -305 | G26: =-SUMIFS(Mapping!G$201:G$289,Mapping!$J$201:$J$289,'Actual data'!$B26)/1000 -> -60 | H26: =-SUMIFS(Mapping!H$201:H$289,Mapping!$J$201:$J$289,'Actual data'!$B26)/1000 -> 0 | I26: =-SUMIFS(Mapping!I$201:I$289,Mapping!$J$201:$J$289,'Actual data'!$B26)/1000 -> 0
B28: EBIT | C28: =+C22+SUM(C25:C26) -> 4530 | D28: =+D22+SUM(D25:D26) -> 5210 | E28: =+E22+SUM(E25:E26) -> 5629 | F28: =+F22+SUM(F25:F26) -> 3524 | G28: =+G22+SUM(G25:G26) -> 5632 | H28: =+H22+SUM(H25:H26) -> 5905 | I28: =+I22+SUM(I25:I26) -> 5725
B29: % Ricavi | C29: =+C28/C$12 -> 0.15689398 | D29: =+D28/D$12 -> 0.17386371 | E29: =+E28/E$12 -> 0.18931827 | F29: =+F28/F$12 -> 0.12350179 | G29: =+G28/G$12 -> 0.19018032 | H29: =+H28/H$12 -> 0.18834524 | I29: =+I28/I$12 -> 0.17683944
B31: Impairment of assets | C31: =SUMIFS(Mapping!C$201:C$289,Mapping!$J$201:$J$289,'Actual data'!$B31)/1000 -> 0 | D31: =SUMIFS(Mapping!D$201:D$289,Mapping!$J$201:$J$289,'Actual data'!$B31)/1000 -> 0 | E31: =SUMIFS(Mapping!E$201:E$289,Mapping!$J$201:$J$289,'Actual data'!$B31)/1000 -> 0 | F31: =SUMIFS(Mapping!F$201:F$289,Mapping!$J$201:$J$289,'Actual data'!$B31)/1000 -> -50 | G31: =SUMIFS(Mapping!G$201:G$289,Mapping!$J$201:$J$289,'Actual data'!$B31)/1000 -> 0 | H31: =SUMIFS(Mapping!H$201:H$289,Mapping!$J$201:$J$289,'Actual data'!$B31)/1000 -> -236 | I31: =SUMIFS(Mapping!I$201:I$289,Mapping!$J$201:$J$289,'Actual data'!$B31)/1000 -> -56
B32: Proventi/(oneri) finanziari | C32: =SUMIFS(Mapping!C$201:C$289,Mapping!$J$201:$J$289,'Actual data'!$B32)/1000 -> -973 | D32: =SUMIFS(Mapping!D$201:D$289,Mapping!$J$201:$J$289,'Actual data'!$B32)/1000 -> -1420 | E32: =SUMIFS(Mapping!E$201:E$289,Mapping!$J$201:$J$289,'Actual data'!$B32)/1000 -> -1627 | F32: =SUMIFS(Mapping!F$201:F$289,Mapping!$J$201:$J$289,'Actual data'!$B32)/1000 -> -1230 | G32: =SUMIFS(Mapping!G$201:G$289,Mapping!$J$201:$J$289,'Actual data'!$B32)/1000 -> -1257 | H32: =SUMIFS(Mapping!H$201:H$289,Mapping!$J$201:$J$289,'Actual data'!$B32)/1000 -> -1393 | I32: =SUMIFS(Mapping!I$201:I$289,Mapping!$J$201:$J$289,'Actual data'!$B32)/1000 -> -1619
B33: Costi straordinari | C33: =SUMIFS(Mapping!C$201:C$289,Mapping!$J$201:$J$289,'Actual data'!$B33)/1000 -> -19 | D33: =SUMIFS(Mapping!D$201:D$289,Mapping!$J$201:$J$289,'Actual data'!$B33)/1000 -> 200 | E33: =SUMIFS(Mapping!E$201:E$289,Mapping!$J$201:$J$289,'Actual data'!$B33)/1000 -> 108 | F33: =SUMIFS(Mapping!F$201:F$289,Mapping!$J$201:$J$289,'Actual data'!$B33)/1000 -> 381 | G33: =SUMIFS(Mapping!G$201:G$289,Mapping!$J$201:$J$289,'Actual data'!$B33)/1000 -> 129 | H33: =SUMIFS(Mapping!H$201:H$289,Mapping!$J$201:$J$289,'Actual data'!$B33)/1000 -> 106 | I33: =SUMIFS(Mapping!I$201:I$289,Mapping!$J$201:$J$289,'Actual data'!$B33)/1000 -> -66
B35: EBT | C35: =+C28+SUM(C31:C33) -> 3538 | D35: =+D28+SUM(D31:D33) -> 3990 | E35: =+E28+SUM(E31:E33) -> 4110 | F35: =+F28+SUM(F31:F33) -> 2625 | G35: =+G28+SUM(G31:G33) -> 4504 | H35: =+H28+SUM(H31:H33) -> 4382 | I35: =+I28+SUM(I31:I33) -> 3984
B37: Imposte | C37: =-SUMIFS(Mapping!C$201:C$289,Mapping!$J$201:$J$289,'Actual data'!$B37)/1000 -> -1085 | D37: =-SUMIFS(Mapping!D$201:D$289,Mapping!$J$201:$J$289,'Actual data'!$B37)/1000 -> -1192 | E37: =-SUMIFS(Mapping!E$201:E$289,Mapping!$J$201:$J$289,'Actual data'!$B37)/1000 -> -1041 | F37: =-SUMIFS(Mapping!F$201:F$289,Mapping!$J$201:$J$289,'Actual data'!$B37)/1000 -> -776 | G37: =-SUMIFS(Mapping!G$201:G$289,Mapping!$J$201:$J$289,'Actual data'!$B37)/1000 -> -508 | H37: =-SUMIFS(Mapping!H$201:H$289,Mapping!$J$201:$J$289,'Actual data'!$B37)/1000 -> -591 | I37: =-SUMIFS(Mapping!I$201:I$289,Mapping!$J$201:$J$289,'Actual data'!$B37)/1000 -> 0
B39: Net result | C39: =+C35+C37 -> 2453 | D39: =+D35+D37 -> 2798 | E39: =+E35+E37 -> 3069 | F39: =+F35+F37 -> 1849 | G39: =+G35+G37 -> 3996 | H39: =+H35+H37 -> 3791 | I39: =+I35+I37 -> 3984
B40: Check | C40: =+C39-Mapping!C285/1000 -> 0 | D40: =+D39-Mapping!D285/1000 -> 0 | E40: =+E39-Mapping!E285/1000 -> 0 | F40: =+F39-Mapping!F285/1000 -> 0 | G40: =+G39-Mapping!G285/1000 -> 0 | H40: =+H39-Mapping!H285/1000 -> 0 | I40: =+I39-Mapping!I285/1000 -> 0
B43: Balance sheet
B45: EUR/000 | C45: 2013 | D45: =+C45+1 -> 2014 | E45: =+D45+1 -> 2015 | F45: =+E45+1 -> 2016 | G45: =+F45+1 -> 2017 | H45: =+G45+1 -> 2018 | I45: =+H45+1 -> 2019
B47: Intangible assets | C47: =+SUMIFS(Mapping!C$5:C$106,Mapping!$J$5:$J$106,'Actual data'!$B47)/1000-SUMIFS(Mapping!C$110:C$191,Mapping!$J$110:$J$191,'Actual data'!$B47)/1000 -> 38 | D47: =+SUMIFS(Mapping!D$5:D$106,Mapping!$J$5:$J$106,'Actual data'!$B47)/1000-SUMIFS(Mapping!D$110:D$191,Mapping!$J$110:$J$191,'Actual data'!$B47)/1000 -> 10 | E47: =+SUMIFS(Mapping!E$5:E$106,Mapping!$J$5:$J$106,'Actual data'!$B47)/1000-SUMIFS(Mapping!E$110:E$191,Mapping!$J$110:$J$191,'Actual data'!$B47)/1000 -> 17 | F47: =+SUMIFS(Mapping!F$5:F$106,Mapping!$J$5:$J$106,'Actual data'!$B47)/1000-SUMIFS(Mapping!F$110:F$191,Mapping!$J$110:$J$191,'Actual data'!$B47)/1000 -> 3846 | G47: =+SUMIFS(Mapping!G$5:G$106,Mapping!$J$5:$J$106,'Actual data'!$B47)/1000-SUMIFS(Mapping!G$110:G$191,Mapping!$J$110:$J$191,'Actual data'!$B47)/1000 -> 17 | H47: =+SUMIFS(Mapping!H$5:H$106,Mapping!$J$5:$J$106,'Actual data'!$B47)/1000-SUMIFS(Mapping!H$110:H$191,Mapping!$J$110:$J$191,'Actual data'!$B47)/1000 -> 13 | I47: =+SUMIFS(Mapping!I$5:I$106,Mapping!$J$5:$J$106,'Actual data'!$B47)/1000-SUMIFS(Mapping!I$110:I$191,Mapping!$J$110:$J$191,'Actual data'!$B47)/1000 -> 3
B48: Goodwill | C48: =+SUMIFS(Mapping!C$5:C$106,Mapping!$J$5:$J$106,'Actual data'!$B48)/1000-SUMIFS(Mapping!C$110:C$191,Mapping!$J$110:$J$191,'Actual data'!$B48)/1000 -> 3821 | D48: =+SUMIFS(Mapping!D$5:D$106,Mapping!$J$5:$J$106,'Actual data'!$B48)/1000-SUMIFS(Mapping!D$110:D$191,Mapping!$J$110:$J$191,'Actual data'!$B48)/1000 -> 3821 | E48: =+SUMIFS(Mapping!E$5:E$106,Mapping!$J$5:$J$106,'Actual data'!$B48)/1000-SUMIFS(Mapping!E$110:E$191,Mapping!$J$110:$J$191,'Actual data'!$B48)/1000 -> 3821 | F48: =+SUMIFS(Mapping!F$5:F$106,Mapping!$J$5:$J$106,'Actual data'!$B48)/1000-SUMIFS(Mapping!F$110:F$191,Mapping!$J$110:$J$191,'Actual data'!$B48)/1000 -> 0 | G48: =+SUMIFS(Mapping!G$5:G$106,Mapping!$J$5:$J$106,'Actual data'!$B48)/1000-SUMIFS(Mapping!G$110:G$191,Mapping!$J$110:$J$191,'Actual data'!$B48)/1000 -> 3821 | H48: =+SUMIFS(Mapping!H$5:H$106,Mapping!$J$5:$J$106,'Actual data'!$B48)/1000-SUMIFS(Mapping!H$110:H$191,Mapping!$J$110:$J$191,'Actual data'!$B48)/1000 -> 3821 | I48: =+SUMIFS(Mapping!I$5:I$106,Mapping!$J$5:$J$106,'Actual data'!$B48)/1000-SUMIFS(Mapping!I$110:I$191,Mapping!$J$110:$J$191,'Actual data'!$B48)/1000 -> 3821
B49: Tangible assets | C49: =+SUMIFS(Mapping!C$5:C$106,Mapping!$J$5:$J$106,'Actual data'!$B49)/1000-SUMIFS(Mapping!C$110:C$191,Mapping!$J$110:$J$191,'Actual data'!$B49)/1000 -> 17960 | D49: =+SUMIFS(Mapping!D$5:D$106,Mapping!$J$5:$J$106,'Actual data'!$B49)/1000-SUMIFS(Mapping!D$110:D$191,Mapping!$J$110:$J$191,'Actual data'!$B49)/1000 -> 25718 | E49: =+SUMIFS(Mapping!E$5:E$106,Mapping!$J$5:$J$106,'Actual data'!$B49)/1000-SUMIFS(Mapping!E$110:E$191,Mapping!$J$110:$J$191,'Actual data'!$B49)/1000 -> 27100 | F49: =+SUMIFS(Mapping!F$5:F$106,Mapping!$J$5:$J$106,'Actual data'!$B49)/1000-SUMIFS(Mapping!F$110:F$191,Mapping!$J$110:$J$191,'Actual data'!$B49)/1000 -> 31281 | G49: =+SUMIFS(Mapping!G$5:G$106,Mapping!$J$5:$J$106,'Actual data'!$B49)/1000-SUMIFS(Mapping!G$110:G$191,Mapping!$J$110:$J$191,'Actual data'!$B49)/1000 -> 31257 | H49: =+SUMIFS(Mapping!H$5:H$106,Mapping!$J$5:$J$106,'Actual data'!$B49)/1000-SUMIFS(Mapping!H$110:H$191,Mapping!$J$110:$J$191,'Actual data'!$B49)/1000 -> 31453 | I49: =+SUMIFS(Mapping!I$5:I$106,Mapping!$J$5:$J$106,'Actual data'!$B49)/1000-SUMIFS(Mapping!I$110:I$191,Mapping!$J$110:$J$191,'Actual data'!$B49)/1000 -> 35954
B50: Attivo fisso | C50: =+SUM(C47:C49) -> 21819 | D50: =+SUM(D47:D49) -> 29549 | E50: =+SUM(E47:E49) -> 30938 | F50: =+SUM(F47:F49) -> 35127 | G50: =+SUM(G47:G49) -> 35095 | H50: =+SUM(H47:H49) -> 35287 | I50: =+SUM(I47:I49) -> 39778
B52: RImanenze | C52: =+SUMIFS(Mapping!C$5:C$106,Mapping!$J$5:$J$106,'Actual data'!$B52)/1000-SUMIFS(Mapping!C$110:C$191,Mapping!$J$110:$J$191,'Actual data'!$B52)/1000 -> 297 | D52: =+SUMIFS(Mapping!D$5:D$106,Mapping!$J$5:$J$106,'Actual data'!$B52)/1000-SUMIFS(Mapping!D$110:D$191,Mapping!$J$110:$J$191,'Actual data'!$B52)/1000 -> 287 | E52: =+SUMIFS(Mapping!E$5:E$106,Mapping!$J$5:$J$106,'Actual data'!$B52)/1000-SUMIFS(Mapping!E$110:E$191,Mapping!$J$110:$J$191,'Actual data'!$B52)/1000 -> 215 | F52: =+SUMIFS(Mapping!F$5:F$106,Mapping!$J$5:$J$106,'Actual data'!$B52)/1000-SUMIFS(Mapping!F$110:F$191,Mapping!$J$110:$J$191,'Actual data'!$B52)/1000 -> 128 | G52: =+SUMIFS(Mapping!G$5:G$106,Mapping!$J$5:$J$106,'Actual data'!$B52)/1000-SUMIFS(Mapping!G$110:G$191,Mapping!$J$110:$J$191,'Actual data'!$B52)/1000 -> 142 | H52: =+SUMIFS(Mapping!H$5:H$106,Mapping!$J$5:$J$106,'Actual data'!$B52)/1000-SUMIFS(Mapping!H$110:H$191,Mapping!$J$110:$J$191,'Actual data'!$B52)/1000 -> 103 | I52: =+SUMIFS(Mapping!I$5:I$106,Mapping!$J$5:$J$106,'Actual data'!$B52)/1000-SUMIFS(Mapping!I$110:I$191,Mapping!$J$110:$J$191,'Actual data'!$B52)/1000 -> 140
B53: Crediti commerciali | C53: =+SUMIFS(Mapping!C$5:C$106,Mapping!$J$5:$J$106,'Actual data'!$B53)/1000-SUMIFS(Mapping!C$110:C$191,Mapping!$J$110:$J$191,'Actual data'!$B53)/1000 -> 21377 | D53: =+SUMIFS(Mapping!D$5:D$106,Mapping!$J$5:$J$106,'Actual data'!$B53)/1000-SUMIFS(Mapping!D$110:D$191,Mapping!$J$110:$J$191,'Actual data'!$B53)/1000 -> 12897 | E53: =+SUMIFS(Mapping!E$5:E$106,Mapping!$J$5:$J$106,'Actual data'!$B53)/1000-SUMIFS(Mapping!E$110:E$191,Mapping!$J$110:$J$191,'Actual data'!$B53)/1000 -> 12153 | F53: =+SUMIFS(Mapping!F$5:F$106,Mapping!$J$5:$J$106,'Actual data'!$B53)/1000-SUMIFS(Mapping!F$110:F$191,Mapping!$J$110:$J$191,'Actual data'!$B53)/1000 -> 12870 | G53: =+SUMIFS(Mapping!G$5:G$106,Mapping!$J$5:$J$106,'Actual data'!$B53)/1000-SUMIFS(Mapping!G$110:G$191,Mapping!$J$110:$J$191,'Actual data'!$B53)/1000 -> 14732 | H53: =+SUMIFS(Mapping!H$5:H$106,Mapping!$J$5:$J$106,'Actual data'!$B53)/1000-SUMIFS(Mapping!H$110:H$191,Mapping!$J$110:$J$191,'Actual data'!$B53)/1000 -> 13653 | I53: =+SUMIFS(Mapping!I$5:I$106,Mapping!$J$5:$J$106,'Actual data'!$B53)/1000-SUMIFS(Mapping!I$110:I$191,Mapping!$J$110:$J$191,'Actual data'!$B53)/1000 -> 17104
B54: Debiti commerciali | C54: =+SUMIFS(Mapping!C$5:C$106,Mapping!$J$5:$J$106,'Actual data'!$B54)/1000-SUMIFS(Mapping!C$110:C$191,Mapping!$J$110:$J$191,'Actual data'!$B54)/1000 -> -7533 | D54: =+SUMIFS(Mapping!D$5:D$106,Mapping!$J$5:$J$106,'Actual data'!$B54)/1000-SUMIFS(Mapping!D$110:D$191,Mapping!$J$110:$J$191,'Actual data'!$B54)/1000 -> -6085 | E54: =+SUMIFS(Mapping!E$5:E$106,Mapping!$J$5:$J$106,'Actual data'!$B54)/1000-SUMIFS(Mapping!E$110:E$191,Mapping!$J$110:$J$191,'Actual data'!$B54)/1000 -> -5865 | F54: =+SUMIFS(Mapping!F$5:F$106,Mapping!$J$5:$J$106,'Actual data'!$B54)/1000-SUMIFS(Mapping!F$110:F$191,Mapping!$J$110:$J$191,'Actual data'!$B54)/1000 -> -6388 | G54: =+SUMIFS(Mapping!G$5:G$106,Mapping!$J$5:$J$106,'Actual data'!$B54)/1000-SUMIFS(Mapping!G$110:G$191,Mapping!$J$110:$J$191,'Actual data'!$B54)/1000 -> -6003 | H54: =+SUMIFS(Mapping!H$5:H$106,Mapping!$J$5:$J$106,'Actual data'!$B54)/1000-SUMIFS(Mapping!H$110:H$191,Mapping!$J$110:$J$191,'Actual data'!$B54)/1000 -> -7598 | I54: =+SUMIFS(Mapping!I$5:I$106,Mapping!$J$5:$J$106,'Actual data'!$B54)/1000-SUMIFS(Mapping!I$110:I$191,Mapping!$J$110:$J$191,'Actual data'!$B54)/1000 -> -6246
B55: Intercompany accounts | C55: =+SUMIFS(Mapping!C$5:C$106,Mapping!$J$5:$J$106,'Actual data'!$B55)/1000-SUMIFS(Mapping!C$110:C$191,Mapping!$J$110:$J$191,'Actual data'!$B55)/1000 -> -1820 | D55: =+SUMIFS(Mapping!D$5:D$106,Mapping!$J$5:$J$106,'Actual data'!$B55)/1000-SUMIFS(Mapping!D$110:D$191,Mapping!$J$110:$J$191,'Actual data'!$B55)/1000 -> 5585 | E55: =+SUMIFS(Mapping!E$5:E$106,Mapping!$J$5:$J$106,'Actual data'!$B55)/1000-SUMIFS(Mapping!E$110:E$191,Mapping!$J$110:$J$191,'Actual data'!$B55)/1000 -> 7024 | F55: =+SUMIFS(Mapping!F$5:F$106,Mapping!$J$5:$J$106,'Actual data'!$B55)/1000-SUMIFS(Mapping!F$110:F$191,Mapping!$J$110:$J$191,'Actual data'!$B55)/1000 -> 1961 | G55: =+SUMIFS(Mapping!G$5:G$106,Mapping!$J$5:$J$106,'Actual data'!$B55)/1000-SUMIFS(Mapping!G$110:G$191,Mapping!$J$110:$J$191,'Actual data'!$B55)/1000 -> 1658 | H55: =+SUMIFS(Mapping!H$5:H$106,Mapping!$J$5:$J$106,'Actual data'!$B55)/1000-SUMIFS(Mapping!H$110:H$191,Mapping!$J$110:$J$191,'Actual data'!$B55)/1000 -> 1223 | I55: =+SUMIFS(Mapping!I$5:I$106,Mapping!$J$5:$J$106,'Actual data'!$B55)/1000-SUMIFS(Mapping!I$110:I$191,Mapping!$J$110:$J$191,'Actual data'!$B55)/1000 -> 4159
B56: Altre attività/passività correnti | C56: =+SUMIFS(Mapping!C$5:C$106,Mapping!$J$5:$J$106,'Actual data'!$B56)/1000-SUMIFS(Mapping!C$110:C$191,Mapping!$J$110:$J$191,'Actual data'!$B56)/1000 -> -883 | D56: =+SUMIFS(Mapping!D$5:D$106,Mapping!$J$5:$J$106,'Actual data'!$B56)/1000-SUMIFS(Mapping!D$110:D$191,Mapping!$J$110:$J$191,'Actual data'!$B56)/1000 -> 809 | E56: =+SUMIFS(Mapping!E$5:E$106,Mapping!$J$5:$J$106,'Actual data'!$B56)/1000-SUMIFS(Mapping!E$110:E$191,Mapping!$J$110:$J$191,'Actual data'!$B56)/1000 -> -2129 | F56: =+SUMIFS(Mapping!F$5:F$106,Mapping!$J$5:$J$106,'Actual data'!$B56)/1000-SUMIFS(Mapping!F$110:F$191,Mapping!$J$110:$J$191,'Actual data'!$B56)/1000 -> -2371 | G56: =+SUMIFS(Mapping!G$5:G$106,Mapping!$J$5:$J$106,'Actual data'!$B56)/1000-SUMIFS(Mapping!G$110:G$191,Mapping!$J$110:$J$191,'Actual data'!$B56)/1000 -> -4538 | H56: =+SUMIFS(Mapping!H$5:H$106,Mapping!$J$5:$J$106,'Actual data'!$B56)/1000-SUMIFS(Mapping!H$110:H$191,Mapping!$J$110:$J$191,'Actual data'!$B56)/1000 -> -3387 | I56: =+SUMIFS(Mapping!I$5:I$106,Mapping!$J$5:$J$106,'Actual data'!$B56)/1000-SUMIFS(Mapping!I$110:I$191,Mapping!$J$110:$J$191,'Actual data'!$B56)/1000 -> -4004
B57: Capitale circolante netto | C57: =+SUM(C52:C56) -> 11438 | D57: =+SUM(D52:D56) -> 13493 | E57: =+SUM(E52:E56) -> 11398 | F57: =+SUM(F52:F56) -> 6200 | G57: =+SUM(G52:G56) -> 5991 | H57: =+SUM(H52:H56) -> 3994 | I57: =+SUM(I52:I56) -> 11153
B59: Attività/passività non correnti | C59: =+SUMIFS(Mapping!C$5:C$106,Mapping!$J$5:$J$106,'Actual data'!$B59)/1000-SUMIFS(Mapping!C$110:C$191,Mapping!$J$110:$J$191,'Actual data'!$B59)/1000 -> 6 | D59: =+SUMIFS(Mapping!D$5:D$106,Mapping!$J$5:$J$106,'Actual data'!$B59)/1000-SUMIFS(Mapping!D$110:D$191,Mapping!$J$110:$J$191,'Actual data'!$B59)/1000 -> 5 | E59: =+SUMIFS(Mapping!E$5:E$106,Mapping!$J$5:$J$106,'Actual data'!$B59)/1000-SUMIFS(Mapping!E$110:E$191,Mapping!$J$110:$J$191,'Actual data'!$B59)/1000 -> 5 | F59: =+SUMIFS(Mapping!F$5:F$106,Mapping!$J$5:$J$106,'Actual data'!$B59)/1000-SUMIFS(Mapping!F$110:F$191,Mapping!$J$110:$J$191,'Actual data'!$B59)/1000 -> 11 | G59: =+SUMIFS(Mapping!G$5:G$106,Mapping!$J$5:$J$106,'Actual data'!$B59)/1000-SUMIFS(Mapping!G$110:G$191,Mapping!$J$110:$J$191,'Actual data'!$B59)/1000 -> 11 | H59: =+SUMIFS(Mapping!H$5:H$106,Mapping!$J$5:$J$106,'Actual data'!$B59)/1000-SUMIFS(Mapping!H$110:H$191,Mapping!$J$110:$J$191,'Actual data'!$B59)/1000 -> 11 | I59: =+SUMIFS(Mapping!I$5:I$106,Mapping!$J$5:$J$106,'Actual data'!$B59)/1000-SUMIFS(Mapping!I$110:I$191,Mapping!$J$110:$J$191,'Actual data'!$B59)/1000 -> 11
B61: Fondi | C61: =+SUMIFS(Mapping!C$5:C$106,Mapping!$J$5:$J$106,'Actual data'!$B61)/1000-SUMIFS(Mapping!C$110:C$191,Mapping!$J$110:$J$191,'Actual data'!$B61)/1000 -> -1511 | D61: =+SUMIFS(Mapping!D$5:D$106,Mapping!$J$5:$J$106,'Actual data'!$B61)/1000-SUMIFS(Mapping!D$110:D$191,Mapping!$J$110:$J$191,'Actual data'!$B61)/1000 -> -1964 | E61: =+SUMIFS(Mapping!E$5:E$106,Mapping!$J$5:$J$106,'Actual data'!$B61)/1000-SUMIFS(Mapping!E$110:E$191,Mapping!$J$110:$J$191,'Actual data'!$B61)/1000 -> -17 | F61: =+SUMIFS(Mapping!F$5:F$106,Mapping!$J$5:$J$106,'Actual data'!$B61)/1000-SUMIFS(Mapping!F$110:F$191,Mapping!$J$110:$J$191,'Actual data'!$B61)/1000 -> -21 | G61: =+SUMIFS(Mapping!G$5:G$106,Mapping!$J$5:$J$106,'Actual data'!$B61)/1000-SUMIFS(Mapping!G$110:G$191,Mapping!$J$110:$J$191,'Actual data'!$B61)/1000 -> -18 | H61: =+SUMIFS(Mapping!H$5:H$106,Mapping!$J$5:$J$106,'Actual data'!$B61)/1000-SUMIFS(Mapping!H$110:H$191,Mapping!$J$110:$J$191,'Actual data'!$B61)/1000 -> -18 | I61: =+SUMIFS(Mapping!I$5:I$106,Mapping!$J$5:$J$106,'Actual data'!$B61)/1000-SUMIFS(Mapping!I$110:I$191,Mapping!$J$110:$J$191,'Actual data'!$B61)/1000 -> -17
B63: Capitale investito netto | C63: =+C50+C57+C59+C61 -> 31752 | D63: =+D50+D57+D59+D61 -> 41083 | E63: =+E50+E57+E59+E61 -> 42324 | F63: =+F50+F57+F59+F61 -> 41317 | G63: =+G50+G57+G59+G61 -> 41079 | H63: =+H50+H57+H59+H61 -> 39274 | I63: =+I50+I57+I59+I61 -> 50925
B65: Patrimonio netto | C65: =-SUMIFS(Mapping!C$5:C$106,Mapping!$J$5:$J$106,'Actual data'!$B65)/1000+SUMIFS(Mapping!C$110:C$191,Mapping!$J$110:$J$191,'Actual data'!$B65)/1000 -> 17007 | D65: =-SUMIFS(Mapping!D$5:D$106,Mapping!$J$5:$J$106,'Actual data'!$B65)/1000+SUMIFS(Mapping!D$110:D$191,Mapping!$J$110:$J$191,'Actual data'!$B65)/1000 -> 19695 | E65: =-SUMIFS(Mapping!E$5:E$106,Mapping!$J$5:$J$106,'Actual data'!$B65)/1000+SUMIFS(Mapping!E$110:E$191,Mapping!$J$110:$J$191,'Actual data'!$B65)/1000 -> 22872 | F65: =-SUMIFS(Mapping!F$5:F$106,Mapping!$J$5:$J$106,'Actual data'!$B65)/1000+SUMIFS(Mapping!F$110:F$191,Mapping!$J$110:$J$191,'Actual data'!$B65)/1000 -> 24689 | G65: =-SUMIFS(Mapping!G$5:G$106,Mapping!$J$5:$J$106,'Actual data'!$B65)/1000+SUMIFS(Mapping!G$110:G$191,Mapping!$J$110:$J$191,'Actual data'!$B65)/1000 -> 28757 | H65: =-SUMIFS(Mapping!H$5:H$106,Mapping!$J$5:$J$106,'Actual data'!$B65)/1000+SUMIFS(Mapping!H$110:H$191,Mapping!$J$110:$J$191,'Actual data'!$B65)/1000 -> 32528 | I65: =-SUMIFS(Mapping!I$5:I$106,Mapping!$J$5:$J$106,'Actual data'!$B65)/1000+SUMIFS(Mapping!I$110:I$191,Mapping!$J$110:$J$191,'Actual data'!$B65)/1000 -> 36461
B67: Passività finanziarie | C67: =-SUMIFS(Mapping!C$5:C$106,Mapping!$J$5:$J$106,'Actual data'!$B67)/1000+SUMIFS(Mapping!C$110:C$191,Mapping!$J$110:$J$191,'Actual data'!$B67)/1000 -> 18726 | D67: =-SUMIFS(Mapping!D$5:D$106,Mapping!$J$5:$J$106,'Actual data'!$B67)/1000+SUMIFS(Mapping!D$110:D$191,Mapping!$J$110:$J$191,'Actual data'!$B67)/1000 -> 23423 | E67: =-SUMIFS(Mapping!E$5:E$106,Mapping!$J$5:$J$106,'Actual data'!$B67)/1000+SUMIFS(Mapping!E$110:E$191,Mapping!$J$110:$J$191,'Actual data'!$B67)/1000 -> 21234 | F67: =-SUMIFS(Mapping!F$5:F$106,Mapping!$J$5:$J$106,'Actual data'!$B67)/1000+SUMIFS(Mapping!F$110:F$191,Mapping!$J$110:$J$191,'Actual data'!$B67)/1000 -> 26072 | G67: =-SUMIFS(Mapping!G$5:G$106,Mapping!$J$5:$J$106,'Actual data'!$B67)/1000+SUMIFS(Mapping!G$110:G$191,Mapping!$J$110:$J$191,'Actual data'!$B67)/1000 -> 23579 | H67: =-SUMIFS(Mapping!H$5:H$106,Mapping!$J$5:$J$106,'Actual data'!$B67)/1000+SUMIFS(Mapping!H$110:H$191,Mapping!$J$110:$J$191,'Actual data'!$B67)/1000 -> 18189 | I67: =-SUMIFS(Mapping!I$5:I$106,Mapping!$J$5:$J$106,'Actual data'!$B67)/1000+SUMIFS(Mapping!I$110:I$191,Mapping!$J$110:$J$191,'Actual data'!$B67)/1000 -> 14006
B68: Passività finanziarie - IC | C68: =-SUMIFS(Mapping!C$5:C$106,Mapping!$J$5:$J$106,'Actual data'!$B68)/1000+SUMIFS(Mapping!C$110:C$191,Mapping!$J$110:$J$191,'Actual data'!$B68)/1000 -> 8755 | D68: =-SUMIFS(Mapping!D$5:D$106,Mapping!$J$5:$J$106,'Actual data'!$B68)/1000+SUMIFS(Mapping!D$110:D$191,Mapping!$J$110:$J$191,'Actual data'!$B68)/1000 -> 13048 | E68: =-SUMIFS(Mapping!E$5:E$106,Mapping!$J$5:$J$106,'Actual data'!$B68)/1000+SUMIFS(Mapping!E$110:E$191,Mapping!$J$110:$J$191,'Actual data'!$B68)/1000 -> 13083 | F68: =-SUMIFS(Mapping!F$5:F$106,Mapping!$J$5:$J$106,'Actual data'!$B68)/1000+SUMIFS(Mapping!F$110:F$191,Mapping!$J$110:$J$191,'Actual data'!$B68)/1000 -> 11711 | G68: =-SUMIFS(Mapping!G$5:G$106,Mapping!$J$5:$J$106,'Actual data'!$B68)/1000+SUMIFS(Mapping!G$110:G$191,Mapping!$J$110:$J$191,'Actual data'!$B68)/1000 -> 30205 | H68: =-SUMIFS(Mapping!H$5:H$106,Mapping!$J$5:$J$106,'Actual data'!$B68)/1000+SUMIFS(Mapping!H$110:H$191,Mapping!$J$110:$J$191,'Actual data'!$B68)/1000 -> 50215 | I68: =-SUMIFS(Mapping!I$5:I$106,Mapping!$J$5:$J$106,'Actual data'!$B68)/1000+SUMIFS(Mapping!I$110:I$191,Mapping!$J$110:$J$191,'Actual data'!$B68)/1000 -> 68813
B69: TFR | C69: =-SUMIFS(Mapping!C$5:C$106,Mapping!$J$5:$J$106,'Actual data'!$B69)/1000+SUMIFS(Mapping!C$110:C$191,Mapping!$J$110:$J$191,'Actual data'!$B69)/1000 -> 905 | D69: =-SUMIFS(Mapping!D$5:D$106,Mapping!$J$5:$J$106,'Actual data'!$B69)/1000+SUMIFS(Mapping!D$110:D$191,Mapping!$J$110:$J$191,'Actual data'!$B69)/1000 -> 1064 | E69: =-SUMIFS(Mapping!E$5:E$106,Mapping!$J$5:$J$106,'Actual data'!$B69)/1000+SUMIFS(Mapping!E$110:E$191,Mapping!$J$110:$J$191,'Actual data'!$B69)/1000 -> 1042 | F69: =-SUMIFS(Mapping!F$5:F$106,Mapping!$J$5:$J$106,'Actual data'!$B69)/1000+SUMIFS(Mapping!F$110:F$191,Mapping!$J$110:$J$191,'Actual data'!$B69)/1000 -> 1079 | G69: =-SUMIFS(Mapping!G$5:G$106,Mapping!$J$5:$J$106,'Actual data'!$B69)/1000+SUMIFS(Mapping!G$110:G$191,Mapping!$J$110:$J$191,'Actual data'!$B69)/1000 -> 1152 | H69: =-SUMIFS(Mapping!H$5:H$106,Mapping!$J$5:$J$106,'Actual data'!$B69)/1000+SUMIFS(Mapping!H$110:H$191,Mapping!$J$110:$J$191,'Actual data'!$B69)/1000 -> 1082 | I69: =-SUMIFS(Mapping!I$5:I$106,Mapping!$J$5:$J$106,'Actual data'!$B69)/1000+SUMIFS(Mapping!I$110:I$191,Mapping!$J$110:$J$191,'Actual data'!$B69)/1000 -> 1310
B70: Attività finanziarie | C70: =-SUMIFS(Mapping!C$5:C$106,Mapping!$J$5:$J$106,'Actual data'!$B70)/1000+SUMIFS(Mapping!C$110:C$191,Mapping!$J$110:$J$191,'Actual data'!$B70)/1000 -> -3 | D70: =-SUMIFS(Mapping!D$5:D$106,Mapping!$J$5:$J$106,'Actual data'!$B70)/1000+SUMIFS(Mapping!D$110:D$191,Mapping!$J$110:$J$191,'Actual data'!$B70)/1000 -> -2 | E70: =-SUMIFS(Mapping!E$5:E$106,Mapping!$J$5:$J$106,'Actual data'!$B70)/1000+SUMIFS(Mapping!E$110:E$191,Mapping!$J$110:$J$191,'Actual data'!$B70)/1000 -> -1 | F70: =-SUMIFS(Mapping!F$5:F$106,Mapping!$J$5:$J$106,'Actual data'!$B70)/1000+SUMIFS(Mapping!F$110:F$191,Mapping!$J$110:$J$191,'Actual data'!$B70)/1000 -> -2894 | G70: =-SUMIFS(Mapping!G$5:G$106,Mapping!$J$5:$J$106,'Actual data'!$B70)/1000+SUMIFS(Mapping!G$110:G$191,Mapping!$J$110:$J$191,'Actual data'!$B70)/1000 -> -2044 | H70: =-SUMIFS(Mapping!H$5:H$106,Mapping!$J$5:$J$106,'Actual data'!$B70)/1000+SUMIFS(Mapping!H$110:H$191,Mapping!$J$110:$J$191,'Actual data'!$B70)/1000 -> -19331 | I70: =-SUMIFS(Mapping!I$5:I$106,Mapping!$J$5:$J$106,'Actual data'!$B70)/1000+SUMIFS(Mapping!I$110:I$191,Mapping!$J$110:$J$191,'Actual data'!$B70)/1000 -> -23165
B71: Attività finanziarie - IC | C71: =-SUMIFS(Mapping!C$5:C$106,Mapping!$J$5:$J$106,'Actual data'!$B71)/1000+SUMIFS(Mapping!C$110:C$191,Mapping!$J$110:$J$191,'Actual data'!$B71)/1000 -> -4052 | D71: =-SUMIFS(Mapping!D$5:D$106,Mapping!$J$5:$J$106,'Actual data'!$B71)/1000+SUMIFS(Mapping!D$110:D$191,Mapping!$J$110:$J$191,'Actual data'!$B71)/1000 -> -2890 | E71: =-SUMIFS(Mapping!E$5:E$106,Mapping!$J$5:$J$106,'Actual data'!$B71)/1000+SUMIFS(Mapping!E$110:E$191,Mapping!$J$110:$J$191,'Actual data'!$B71)/1000 -> -1803 | F71: =-SUMIFS(Mapping!F$5:F$106,Mapping!$J$5:$J$106,'Actual data'!$B71)/1000+SUMIFS(Mapping!F$110:F$191,Mapping!$J$110:$J$191,'Actual data'!$B71)/1000 -> 0 | G71: =-SUMIFS(Mapping!G$5:G$106,Mapping!$J$5:$J$106,'Actual data'!$B71)/1000+SUMIFS(Mapping!G$110:G$191,Mapping!$J$110:$J$191,'Actual data'!$B71)/1000 -> -136 | H71: =-SUMIFS(Mapping!H$5:H$106,Mapping!$J$5:$J$106,'Actual data'!$B71)/1000+SUMIFS(Mapping!H$110:H$191,Mapping!$J$110:$J$191,'Actual data'!$B71)/1000 -> -281 | I71: =-SUMIFS(Mapping!I$5:I$106,Mapping!$J$5:$J$106,'Actual data'!$B71)/1000+SUMIFS(Mapping!I$110:I$191,Mapping!$J$110:$J$191,'Actual data'!$B71)/1000 -> 0
B72: Cash and cash equivalents | C72: =-SUMIFS(Mapping!C$5:C$106,Mapping!$J$5:$J$106,'Actual data'!$B72)/1000+SUMIFS(Mapping!C$110:C$191,Mapping!$J$110:$J$191,'Actual data'!$B72)/1000 -> -111 | D72: =-SUMIFS(Mapping!D$5:D$106,Mapping!$J$5:$J$106,'Actual data'!$B72)/1000+SUMIFS(Mapping!D$110:D$191,Mapping!$J$110:$J$191,'Actual data'!$B72)/1000 -> -510 | E72: =-SUMIFS(Mapping!E$5:E$106,Mapping!$J$5:$J$106,'Actual data'!$B72)/1000+SUMIFS(Mapping!E$110:E$191,Mapping!$J$110:$J$191,'Actual data'!$B72)/1000 -> -283 | F72: =-SUMIFS(Mapping!F$5:F$106,Mapping!$J$5:$J$106,'Actual data'!$B72)/1000+SUMIFS(Mapping!F$110:F$191,Mapping!$J$110:$J$191,'Actual data'!$B72)/1000 -> -2988 | G72: =-SUMIFS(Mapping!G$5:G$106,Mapping!$J$5:$J$106,'Actual data'!$B72)/1000+SUMIFS(Mapping!G$110:G$191,Mapping!$J$110:$J$191,'Actual data'!$B72)/1000 -> -337 | H72: =-SUMIFS(Mapping!H$5:H$106,Mapping!$J$5:$J$106,'Actual data'!$B72)/1000+SUMIFS(Mapping!H$110:H$191,Mapping!$J$110:$J$191,'Actual data'!$B72)/1000 -> -205 | I72: =-SUMIFS(Mapping!I$5:I$106,Mapping!$J$5:$J$106,'Actual data'!$B72)/1000+SUMIFS(Mapping!I$110:I$191,Mapping!$J$110:$J$191,'Actual data'!$B72)/1000 -> -101
B73: Posizione finanziaria netta | C73: =+SUM(C67:C72) -> 24220 | D73: =+SUM(D67:D72) -> 34133 | E73: =+SUM(E67:E72) -> 33272 | F73: =+SUM(F67:F72) -> 32980 | G73: =+SUM(G67:G72) -> 52419 | H73: =+SUM(H67:H72) -> 49669 | I73: =+SUM(I67:I72) -> 60863
B75: Partecipazioni | C75: =-SUMIFS(Mapping!C$5:C$106,Mapping!$J$5:$J$106,'Actual data'!$B75)/1000+SUMIFS(Mapping!C$110:C$191,Mapping!$J$110:$J$191,'Actual data'!$B75)/1000 -> -8626 | D75: =-SUMIFS(Mapping!D$5:D$106,Mapping!$J$5:$J$106,'Actual data'!$B75)/1000+SUMIFS(Mapping!D$110:D$191,Mapping!$J$110:$J$191,'Actual data'!$B75)/1000 -> -11723 | E75: =-SUMIFS(Mapping!E$5:E$106,Mapping!$J$5:$J$106,'Actual data'!$B75)/1000+SUMIFS(Mapping!E$110:E$191,Mapping!$J$110:$J$191,'Actual data'!$B75)/1000 -> -12672 | F75: =-SUMIFS(Mapping!F$5:F$106,Mapping!$J$5:$J$106,'Actual data'!$B75)/1000+SUMIFS(Mapping!F$110:F$191,Mapping!$J$110:$J$191,'Actual data'!$B75)/1000 -> -14920 | G75: =-SUMIFS(Mapping!G$5:G$106,Mapping!$J$5:$J$106,'Actual data'!$B75)/1000+SUMIFS(Mapping!G$110:G$191,Mapping!$J$110:$J$191,'Actual data'!$B75)/1000 -> -38484 | H75: =-SUMIFS(Mapping!H$5:H$106,Mapping!$J$5:$J$106,'Actual data'!$B75)/1000+SUMIFS(Mapping!H$110:H$191,Mapping!$J$110:$J$191,'Actual data'!$B75)/1000 -> -41017 | I75: =-SUMIFS(Mapping!I$5:I$106,Mapping!$J$5:$J$106,'Actual data'!$B75)/1000+SUMIFS(Mapping!I$110:I$191,Mapping!$J$110:$J$191,'Actual data'!$B75)/1000 -> -44567
B77: Imposte differite | C77: =-SUMIFS(Mapping!C$5:C$106,Mapping!$J$5:$J$106,'Actual data'!$B77)/1000+SUMIFS(Mapping!C$110:C$191,Mapping!$J$110:$J$191,'Actual data'!$B77)/1000 -> -849 | D77: =-SUMIFS(Mapping!D$5:D$106,Mapping!$J$5:$J$106,'Actual data'!$B77)/1000+SUMIFS(Mapping!D$110:D$191,Mapping!$J$110:$J$191,'Actual data'!$B77)/1000 -> -1022 | E77: =-SUMIFS(Mapping!E$5:E$106,Mapping!$J$5:$J$106,'Actual data'!$B77)/1000+SUMIFS(Mapping!E$110:E$191,Mapping!$J$110:$J$191,'Actual data'!$B77)/1000 -> -1148 | F77: =-SUMIFS(Mapping!F$5:F$106,Mapping!$J$5:$J$106,'Actual data'!$B77)/1000+SUMIFS(Mapping!F$110:F$191,Mapping!$J$110:$J$191,'Actual data'!$B77)/1000 -> -1432 | G77: =-SUMIFS(Mapping!G$5:G$106,Mapping!$J$5:$J$106,'Actual data'!$B77)/1000+SUMIFS(Mapping!G$110:G$191,Mapping!$J$110:$J$191,'Actual data'!$B77)/1000 -> -1613 | H77: =-SUMIFS(Mapping!H$5:H$106,Mapping!$J$5:$J$106,'Actual data'!$B77)/1000+SUMIFS(Mapping!H$110:H$191,Mapping!$J$110:$J$191,'Actual data'!$B77)/1000 -> -1906 | I77: =-SUMIFS(Mapping!I$5:I$106,Mapping!$J$5:$J$106,'Actual data'!$B77)/1000+SUMIFS(Mapping!I$110:I$191,Mapping!$J$110:$J$191,'Actual data'!$B77)/1000 -> -1832
B79: Fonti di finanziamento | C79: =+C65+C73+C75+C77 -> 31752 | D79: =+D65+D73+D75+D77 -> 41083 | E79: =+E65+E73+E75+E77 -> 42324 | F79: =+F65+F73+F75+F77 -> 41317 | G79: =+G65+G73+G75+G77 -> 41079 | H79: =+H65+H73+H75+H77 -> 39274 | I79: =+I65+I73+I75+I77 -> 50925
B80: Check | C80: =+C79-C63 -> 0 | D80: =+D79-D63 -> 0 | E80: =+E79-E63 -> 0 | F80: =+F79-F63 -> 0 | G80: =+G79-G63 -> 0 | H80: =+H79-H63 -> 0 | I80: =+I79-I63 -> 0
B83: Cash flow statement
B85: EUR/000 | C85: 2013 | D85: =+C85+1 -> 2014 | E85: =+D85+1 -> 2015 | F85: =+E85+1 -> 2016 | G85: =+F85+1 -> 2017 | H85: =+G85+1 -> 2018 | I85: =+H85+1 -> 2019
B87: EBITDA | D87: =+D22 -> 10871 | E87: =+E22 -> 11277 | F87: =+F22 -> 8846 | G87: =+G22 -> 12224 | H87: =+H22 -> 11939 | I87: =+I22 -> 11918
B89: Delta in NWC | D89: =+C57-D57 -> -2055 | E89: =+D57-E57 -> 2095 | F89: =+E57-F57 -> 5198 | G89: =+F57-G57 -> 209 | H89: =+G57-H57 -> 1997 | I89: =+H57-I57 -> -7159
B90: Capex | D90: =+C50-D50+D25 -> -12923 | E90: =+D50-E50+E25 -> -6684 | F90: =+E50-F50+F25 -> -9206 | G90: =+F50-G50+G25 -> -6500 | H90: =+G50-H50+H25 -> -6226 | I90: =+H50-I50+I25 -> -10684
B91: Delta in altre attività/passività | D91: =+C59-D59 -> 1 | E91: =+D59-E59 -> 0 | F91: =+E59-F59 -> -6 | G91: =+F59-G59 -> 0 | H91: =+G59-H59 -> 0 | I91: =+H59-I59 -> 0
B92: Fondi | D92: =+C61-D61+D26 -> -15 | E92: =+D61-E61+E26 -> -2300 | F92: =+E61-F61+F26 -> -301 | G92: =+F61-G61+G26 -> -63 | H92: =+G61-H61+H26 -> 0 | I92: =+H61-I61+I26 -> -1
B93: Taxation | D93: =+D37+D77-C77 -> -1365 | E93: =+E37+E77-D77 -> -1167 | F93: =+F37+F77-E77 -> -1060 | G93: =+G37+G77-F77 -> -689 | H93: =+H37+H77-G77 -> -884 | I93: =+I37+I77-H77 -> 74
B94: Costi straordinari | D94: =+D33 -> 200 | E94: =+E33 -> 108 | F94: =+F33 -> 381 | G94: =+G33 -> 129 | H94: =+H33 -> 106 | I94: =+I33 -> -66
B96: Operating cash flow | D96: =+D87+SUM(D89:D94) -> -5286 | E96: =+E87+SUM(E89:E94) -> 3329 | F96: =+F87+SUM(F89:F94) -> 3852 | G96: =+G87+SUM(G89:G94) -> 5310 | H96: =+H87+SUM(H89:H94) -> 6932 | I96: =+I87+SUM(I89:I94) -> -5918
B98: Proventi/(oneri) finanziari | D98: =+D32 -> -1420 | E98: =+E32 -> -1627 | F98: =+F32 -> -1230 | G98: =+G32 -> -1257 | H98: =+H32 -> -1393 | I98: =+I32 -> -1619
B99: Delta in financial attività/passività | D99: =+SUM(D67:D71)-SUM(C67:C71)+D31 -> 10312 | E99: =+SUM(E67:E71)-SUM(D67:D71)+E31 -> -1088 | F99: =+SUM(F67:F71)-SUM(E67:E71)+F31 -> 2363 | G99: =+SUM(G67:G71)-SUM(F67:F71)+G31 -> 16788 | H99: =+SUM(H67:H71)-SUM(G67:G71)+H31 -> -3118 | I99: =+SUM(I67:I71)-SUM(H67:H71)+I31 -> 11034
B100: Delta in Partecipazioni | D100: =+D75-C75 -> -3097 | E100: =+E75-D75 -> -949 | F100: =+F75-E75 -> -2248 | G100: =+G75-F75 -> -23564 | H100: =+H75-G75 -> -2533 | I100: =+I75-H75 -> -3550
B101: Equity movements | D101: =+D65-C65-D39 -> -110 | E101: =+E65-D65-E39 -> 108 | F101: =+F65-E65-F39 -> -32 | G101: =+G65-F65-G39 -> 72 | H101: =+H65-G65-H39 -> -20 | I101: =+I65-H65-I39 -> -51
B103: Financing | D103: =+SUM(D98:D101) -> 5685 | E103: =+SUM(E98:E101) -> -3556 | F103: =+SUM(F98:F101) -> -1147 | G103: =+SUM(G98:G101) -> -7961 | H103: =+SUM(H98:H101) -> -7064 | I103: =+SUM(I98:I101) -> 5814
B105: Delta in cash and cash equivalents | D105: =+D96+D103 -> 399 | E105: =+E96+E103 -> -227 | F105: =+F96+F103 -> 2705 | G105: =+G96+G103 -> -2651 | H105: =+H96+H103 -> -132 | I105: =+I96+I103 -> -104
B106: Check | D106: =+D72-C72+D105 -> 0 | E106: =+E72-D72+E105 -> 0 | F106: =+F72-E72+F105 -> 0 | G106: =+G72-F72+G105 -> 0 | H106: =+H72-G72+H105 -> 0 | I106: =+I72-H72+I105 -> 0

Sheet Mapping
B3: Bilancio non consolidato | C3: 31/12/2013 EUR | D3: 31/12/2014 EUR | E3: 31/12/2015 EUR | F3: 31/12/2016 EUR | G3: 31/12/2017 EUR | H3: 31/12/2018 EUR | I3: 31/12/2019 EUR
C4: 12 mesi Dettagliato Origin. IFRS ICS | D4: 12 mesi Dettagliato Origin. IFRS ICS | E4: 12 mesi Dettagliato Origin. IFRS ICS | F4: 12 mesi Dettagliato Origin. IFRS ICS | G4: 12 mesi Dettagliato Origin. IFRS ICS | H4: 12 mesi Dettagliato Origin. IFRS ICS | I4: 12 mesi Dettagliato Origin. IFRS ICS | J4: Mapping
B5: Attivo
B6: A. CREDITI VERSO SOCI | C6: 0 | D6: 0 | E6: 0 | F6: 0 | G6: 0 | H6: 0 | I6: 0
B7: Quota di capitale richiamata | C7: 0 | D7: 0 | E7: 0 | F7: 0 | G7: 0 | H7: 0 | I7: 0
B9: B. TOTALE IMMOBILIZZAZIONI sep.ind. Di quelle conc. In loc. Finanz. | C9: 34503000 | D9: 44167000 | E9: 45418000 | F9: 50058000 | G9: 73726000 | H9: 76596000 | I9: 84356000
B10: B.I. TOTALE IMMOB. IMMATERIALI | C10: 3859000 | D10: 3831000 | E10: 3838000 | F10: 3846000 | G10: 3838000 | H10: 3834000 | I10: 3824000
B11: B.I.1. Costi impianto e ampl. | C11: 0 | D11: 0 | E11: 0 | F11: 0 | G11: 0 | H11: 0 | I11: 0 | J11: Intangible assets
B12: B.I.2. Costi ricerca e pubb. | C12: 0 | D12: 0 | E12: 0 | F12: 0 | G12: 0 | H12: 0 | I12: 0 | J12: Intangible assets
B13: B.I.3. Diritti brevetto ind. | C13: 0 | D13: 0 | E13: 0 | F13: 0 | G13: 0 | H13: 0 | I13: 0 | J13: Intangible assets
B14: B.I.4. Concessioni, licenze | C14: 38000 | D14: 10000 | E14: 17000 | F14: 25000 | G14: 17000 | H14: 13000 | I14: 3000 | J14: Intangible assets
B15: B.I.5. Avviamento/Differenza di consolidamento | C15: 3821000 | D15: 3821000 | E15: 3821000 | F15: 0 | G15: 3821000 | H15: 3821000 | I15: 3821000 | J15: Goodwill
B16: di cui: Avviamento | C16: 3821000 | D16: 3821000 | E16: 3821000 | G16: 3821000 | H16: 3821000 | I16: 3821000
B17: B.I.6. Imm. in corso | C17: 0 | D17: 0 | E17: 0 | F17: 0 | G17: 0 | H17: 0 | I17: 0 | J17: Intangible assets
B18: B.I.7. Altre immobiliz. Immateriali | C18: 0 | D18: 0 | E18: 0 | F18: 3821000 | G18: 0 | H18: 0 | I18: 0 | J18: Intangible assets
B19: Fondo amm.to Immob. Immateriali | C19: 333000 | D19: 379000 | E19: 382000 | F19: 378000 | H19: 430000
B21: B.II. TOTALE IMMOB. MATERIALI | C21: 17960000 | D21: 25718000 | E21: 27100000 | F21: 31281000 | G21: 31257000 | H21: 31453000 | I21: 35954000
B22: di cui: Beni materiali concessi in locazione finanziaria
B23: B.II.1. Terreni e fabbricati | C23: 0 | D23: 0 | E23: 0 | F23: 0 | G23: 0 | H23: 0 | I23: 0 | J23: Tangible assets
B24: B.II.2. Impianti | C24: 14704000 | D24: 0 | E24: 18668000 | F24: 26000000 | G24: 24835000 | H24: 20527000 | I24: 28887000 | J24: Tangible assets
B25: B.II.3. Attrez. industriali | C25: 696000 | D25: 0 | E25: 1407000 | F25: 1700000 | G25: 1609000 | H25: 1694000 | I25: 2132000 | J25: Tangible assets
B26: B.II.4. Altri beni | C26: 2560000 | D26: 25718000 | E26: 4195000 | F26: 3523000 | G26: 2935000 | H26: 2321000 | I26: 3289000 | J26: Tangible assets
B27: B.II.5. Imm. in corso/acconti | C27: 0 | D27: 0 | E27: 2830000 | F27: 58000 | G27: 1878000 | H27: 6911000 | I27: 1646000 | J27: Tangible assets
B28: Fondo amm.to Immob. Materiali | C28: 25896000 | D28: 30623000 | E28: 32691000 | F28: 32181000 | G28: 37337000 | H28: 43318000 | I28: 43689000
B30: B.III. TOTALE IMMOB. FINANZIARIE | C30: 12684000 | D30: 14618000 | E30: 14480000 | F30: 14931000 | G30: 38631000 | H30: 41309000 | I30: 44578000
B31: di cui: esigibili entro l'esercizio successivo | G31: 136000 | H31: 281000 | I31: 0
B32: B.III.1. TOT Partecipazioni | C32: 8626000 | D32: 11723000 | E32: 12672000 | F32: 14920000 | G32: 38484000 | H32: 41017000 | I32: 44567000
B33: B.III.1.a. Imprese controllate | C33: 8621000 | D33: 11667000 | E33: 12616000 | F33: 14914000 | G33: 38478000 | H33: 41012000 | I33: 44562000 | J33: Partecipazioni
B34: B.III.1.b. Imprese collegate | C34: 0 | D34: 0 | E34: 0 | F34: 0 | G34: 0 | H34: 0 | I34: 0 | J34: Partecipazioni
B35: B.III.1.c. Imprese controllanti | C35: 0 | D35: 0 | E35: 0 | F35: 0 | G35: 0 | H35: 0 | I35: 0 | J35: Partecipazioni
B36: B.III.1.d. In imprese sottoposte al controllo delle controllanti | F36: 0 | G36: 0 | H36: 0 | I36: 0 | J36: Partecipazioni
B37: B.III.1.d.bis. Altre imprese | C37: 5000 | D37: 56000 | E37: 56000 | F37: 6000 | G37: 6000 | H37: 5000 | I37: 5000 | J37: Partecipazioni
B38: B.III.2. TOT CREDITI Imm. Fin. | C38: 4058000 | D38: 2895000 | E38: 1808000 | F38: 11000 | G38: 147000 | H38: 292000 | I38: 11000
B39: B.III.2.a. Cred. vs Controllate entro | C39: 0 | D39: 0 | E39: 0 | F39: 0 | G39: 0 | H39: 0 | I39: 0 | J39: Attività finanziarie - IC
B40: B.III.2.a. Cred. vs Controllate oltre | C40: 4052000 | D40: 2750000 | E40: 1750000 | F40: 0 | G40: 0 | H40: 0 | I40: 0 | J40: Attività finanziarie - IC
B41: B.III.2.b. Cred. vs Collegate entro | C41: 0 | D41: 0 | E41: 0 | F41: 0 | G41: 0 | H41: 0 | I41: 0 | J41: Attività finanziarie - IC
B42: B.III.2.b. Cred. vs Collegate oltre | C42: 0 | D42: 0 | E42: 0 | F42: 0 | G42: 0 | H42: 0 | I42: 0 | J42: Attività finanziarie - IC
B43: B.III.2.c. Cred. vs Controllanti entro | C43: 0 | D43: 0 | E43: 0 | F43: 0 | G43: 136000 | H43: 281000 | I43: 0 | J43: Attività finanziarie - IC
B44: B.III.2.c. Cred. vs Controllanti oltre | C44: 0 | D44: 140000 | E44: 53000 | F44: 0 | G44: 0 | H44: 0 | I44: 0 | J44: Attività finanziarie - IC
B45: B.III.2.d. Cred. vs imprese sottoposte al controllo delle controllanti entro | F45: 0 | G45: 0 | H45: 0 | I45: 0 | J45: Attività finanziarie - IC
B46: B.III.2.d. Cred. vs imprese sottoposte al controllo delle controllanti oltre | F46: 0 | G46: 0 | H46: 0 | I46: 0 | J46: Attività finanziarie - IC
B47: B.III.2.d.bis. Cred. vs Altri entro | C47: 0 | D47: 0 | E47: 0 | F47: 0 | G47: 0 | H47: 0 | I47: 0 | J47: Attività/passività non correnti
B48: B.III.2.d.bis Cred. vs Altri oltre | C48: 6000 | D48: 5000 | E48: 5000 | F48: 11000 | G48: 11000 | H48: 11000 | I48: 11000 | J48: Attività/passività non correnti
B49: B.III. CREDITI FIN. A BREVE | C49: 0 | D49: 0 | E49: 0 | F49: 0 | G49: 136000 | H49: 281000 | I49: 0
B50: B.III. CREDITI FIN. A OLTRE | C50: 4058000 | D50: 2895000 | E50: 1808000 | F50: 11000 | G50: 11000 | H50: 11000 | I50: 11000
B51: B.III.3. Altri titoli | C51: 0 | D51: 0 | E51: 0 | F51: 0 | G51: 0 | H51: 0 | I51: 0
B52: B.III.3.bis. Azioni proprie | C52: 0 | D52: 0 | E52: 0 | F52: 0 | G52: 0 | H52: 0 | I52: 0
B53: B.III.4. Strumenti finanziari derivati attivi | F53: 0 | G53: 0 | H53: 0 | I53: 0
B54: Azioni proprie DI CUI: Val nominale | C54: 0 | D54: 0 | E54: 0 | F54: 0 | G54: 0 | H54: 0 | I54: 0
B56: C. ATTIVO CIRCOLANTE | C56: 23980000 | D56: 24655000 | E56: 23407000 | F56: 23549000 | G56: 21580000 | H56: 37424000 | I56: 47021000
B57: C.I. TOTALE RIMANENZE | C57: 297000 | D57: 287000 | E57: 215000 | F57: 128000 | G57: 142000 | H57: 103000 | I57: 140000
B58: C.I.1. Materie prime | C58: 297000 | D58: 287000 | E58: 215000 | F58: 128000 | G58: 142000 | H58: 103000 | I58: 140000 | J58: RImanenze
B59: C.I.2. Prodotti semilav./in corso | C59: 0 | D59: 0 | E59: 0 | F59: 0 | G59: 0 | H59: 0 | I59: 0 | J59: RImanenze
B60: C.I.3. Lavori in corso | C60: 0 | D60: 0 | E60: 0 | F60: 0 | G60: 0 | H60: 0 | I60: 0 | J60: RImanenze
B61: C.I.4. Prodotti finiti | C61: 0 | D61: 0 | E61: 0 | F61: 0 | G61: 0 | H61: 0 | I61: 0 | J61: RImanenze
B62: C.I.5. Acconti | C62: 0 | D62: 0 | E62: 0 | F62: 0 | G62: 0 | H62: 0 | I62: 0 | J62: RImanenze
B63: Immobilizzazioni materiali destinate alla vendita | F63: 0 | G63: 0 | H63: 0 | I63: 0 | J63: RImanenze
B65: C.II. TOTALE CREDITI | C65: 23569000 | D65: 23856000 | E65: 22908000 | F65: 17539000 | G65: 19057000 | H65: 17785000 | I65: 23615000
B66: C.II.1. Cred. vs Clienti entro | C66: 21377000 | D66: 12897000 | E66: 12153000 | F66: 12870000 | G66: 14732000 | H66: 13653000 | I66: 17104000 | J66: Crediti commerciali
B67: C.II.1. Cred. vs Clienti oltre | C67: 0 | D67: 0 | E67: 0 | F67: 0 | G67: 0 | H67: 0 | I67: 0 | J67: Crediti commerciali
B68: C.II.2. Cred. vs Controllate entro | C68: 0 | D68: 6842000 | E68: 8071000 | F68: 1949000 | G68: 1790000 | H68: 1627000 | I68: 2521000 | J68: Intercompany accounts
B69: C.II.2. Cred. vs Controllate oltre | C69: 0 | D69: 0 | E69: 0 | F69: 0 | G69: 0 | H69: 0 | I69: 0 | J69: Intercompany accounts
B70: C.II.3. Cred. vs Collegate entro | C70: 302000 | D70: 499000 | E70: 0 | F70: 510000 | G70: 0 | H70: 0 | I70: 592000 | J70: Intercompany accounts
B71: C.II.3. Cred. vs Collegate oltre | C71: 0 | D71: 0 | E71: 0 | F71: 32000 | G71: 0 | H71: 0 | I71: 207000 | J71: Intercompany accounts
B72: C.II.4. Cred. vs Controllanti entro | C72: 0 | D72: 0 | E72: 21000 | F72: 0 | G72: 0 | H72: 0 | I72: 879000 | J72: Intercompany accounts
B73: C.II.4. Cred. vs Controllanti oltre | C73: 0 | D73: 0 | E73: 0 | F73: 0 | G73: 0 | H73: 0 | I73: 0 | J73: Intercompany accounts
B74: C.II.5. Cred. vs imprese sottoposte al controllo delle controllanti entro | F74: 0 | G74: 0 | H74: 0 | I74: 0 | J74: Intercompany accounts
B75: C.II.5. Cred. vs imprese sottoposte al controllo delle controllanti oltre | F75: 0 | G75: 0 | H75: 0 | I75: 0 | J75: Intercompany accounts
B76: C.II.5.bis. Cred. tributari entro | C76: 1000 | D76: 1000 | E76: 241000 | F76: 52000 | G76: 155000 | H76: 57000 | I76: 117000 | J76: Altre attività/passività correnti
B77: C.II.5.bis. Cred. tributari oltre | C77: 0 | D77: 0 | E77: 0 | F77: 0 | G77: 0 | H77: 0 | I77: 0 | J77: Altre attività/passività correnti
B78: C.II.5.ter. Cred. per imposte anticipate entro | C78: 0 | D78: 0 | E78: 0 | F78: 0 | G78: 0 | H78: 0 | I78: 0 | J78: Altre attività/passività correnti
B79: C.II.5.ter. Cred. per imposte anticipate oltre | C79: 849000 | D79: 1022000 | E79: 1148000 | F79: 1432000 | G79: 1613000 | H79: 1906000 | I79: 1832000 | J79: Imposte differite
B80: C.II.5.quater. Cred. verso altri entro | C80: 1040000 | D80: 2595000 | E80: 1274000 | F80: 694000 | G80: 767000 | H80: 542000 | I80: 363000 | J80: Altre attività/passività correnti
B81: C.II.5.quater. Cred. verso altri oltre | C81: 0 | D81: 0 | E81: 0 | F81: 0 | G81: 0 | H81: 0 | I81: 0 | J81: Altre attività/passività correnti
B82: C.II. Crediti a breve | C82: 22720000 | D82: 22834000 | E82: 21760000 | F82: 16075000 | G82: 17444000 | H82: 15879000 | I82: 21576000
B83: Crediti per imposte anticipate
B84: C.II. Crediti a oltre | C84: 849000 | D84: 1022000 | E84: 1148000 | F84: 1464000 | G84: 1613000 | H84: 1906000 | I84: 2039000
B86: C.III. TOTALE ATTIVITA' FINANZIARIE | C86: 3000 | D86: 2000 | E86: 1000 | F86: 2894000 | G86: 2044000 | H86: 19331000 | I86: 23165000
B87: C.III.1. Partec.ni in Controllate | C87: 0 | D87: 0 | E87: 0 | F87: 0 | G87: 0 | H87: 0 | I87: 0 | J87: Attività finanziarie
B88: C.III.2. Partec.ni in Collegate | C88: 0 | D88: 0 | E88: 0 | F88: 0 | G88: 0 | H88: 0 | I88: 0 | J88: Attività finanziarie
B89: C.III.3. Partec.ni in Controllanti | C89: 0 | D89: 0 | E89: 0 | F89: 0 | G89: 0 | H89: 0 | I89: 0 | J89: Attività finanziarie
B90: C.III.3.bis. Partec.ni in imprese sottoposte al controllo delle controllanti | F90: 0 | G90: 0 | H90: 0 | I90: 0 | J90: Attività finanziarie
B91: C.III.4. Altre Partec.ni | C91: 0 | D91: 0 | E91: 0 | F91: 0 | G91: 0 | H91: 0 | I91: 0 | J91: Attività finanziarie
B92: C.III.4.bis. Azioni proprie | C92: 0 | D92: 0 | E92: 0 | F92: 0 | G92: 0 | H92: 0 | I92: 0 | J92: Attività finanziarie
B93: Azioni proprie DI CUI: Val nominale | C93: 0 | D93: 0 | E93: 0 | F93: 0 | G93: 0 | H93: 0 | I93: 0
B94: C.III.5. Strumenti finanziari derivati attivi | F94: 1000 | G94: 1000 | H94: 1000 | I94: 0 | J94: Attività finanziarie
B95: C.III.6. Altri titoli | C95: 3000 | D95: 2000 | E95: 1000 | F95: 0 | G95: 0 | H95: 0 | I95: 0 | J95: Attività finanziarie
B96: C.III.7. Attività finanziarie per la gestione accentrata della tesoreria | F96: 2893000 | G96: 2043000 | H96: 19330000 | I96: 23165000 | J96: Attività finanziarie
B98: C.IV. TOT. DISPON. LIQUIDE | C98: 111000 | D98: 510000 | E98: 283000 | F98: 2988000 | G98: 337000 | H98: 205000 | I98: 101000
B99: C.IV.1. Depositi bancari | C99: 101000 | D99: 499000 | E99: 271000 | F99: 2972000 | G99: 300000 | H99: 179000 | I99: 91000 | J99: Cash and cash equivalents
B100: C.IV.2. Assegni | C100: 0 | D100: 0 | E100: 0 | F100: 0 | G100: 0 | H100: 0 | I100: 0 | J100: Cash and cash equivalents
B101: C.IV.3. Denaro in cassa | C101: 10000 | D101: 11000 | E101: 12000 | F101: 16000 | G101: 37000 | H101: 26000 | I101: 10000 | J101: Cash and cash equivalents
B103: D. RATEI E RISCONTI | C103: 0 | D103: 0 | E103: 0 | F103: 0 | G103: 0 | H103: 0 | I103: 0 | J103: Altre attività/passività correnti
B104: Disaggio su prestiti | C104: 0 | D104: 0 | E104: 0 | F104: 0 | G104: 0 | H104: 0 | I104: 0
B106: TOTALE ATTIVO | C106: 58483000 | D106: 68822000 | E106: 68825000 | F106: 73607000 | G106: 95306000 | H106: 114020000 | I106: 131377000
B108: Passivo
B110: PATRIMONIO NETTO
B112: A. TOTALE PATRIMONIO NETTO | C112: 17007000 | D112: 19695000 | E112: 22872000 | F112: 24689000 | G112: 28757000 | H112: 32528000 | I112: 36461000 | J112: Patrimonio netto
B113: A.I. Capitale sociale | C113: 700000 | D113: 700000 | E113: 700000 | F113: 700000 | G113: 700000 | H113: 700000 | I113: 700000
B114: di cui: Versamenti soci in c/capitale | C114: 8291000 | D114: 8291000 | E114: 8291000 | G114: 8291000 | H114: 8291000 | I114: 0
...

Sheet Aida export
B3: Bilancio non consolidato | C3: 31/12/2013 EUR | D3: 31/12/2014 EUR | E3: 31/12/2015 EUR | F3: 31/12/2016 EUR | G3: 31/12/2017 EUR | H3: 31/12/2018 EUR | I3: 31/12/2019 EUR
C4: 12 mesi Dettagliato Origin. IFRS ICS | D4: 12 mesi Dettagliato Origin. IFRS ICS | E4: 12 mesi Dettagliato Origin. IFRS ICS | F4: 12 mesi Dettagliato Origin. IFRS ICS | G4: 12 mesi Dettagliato Origin. IFRS ICS | H4: 12 mesi Dettagliato Origin. IFRS ICS | I4: 12 mesi Dettagliato Origin. IFRS ICS
B5: Attivo
B6: A. CREDITI VERSO SOCI | C6: 0 | D6: 0 | E6: 0 | F6: 0 | G6: 0 | H6: 0 | I6: 0
B7: Quota di capitale richiamata | C7: 0 | D7: 0 | E7: 0 | F7: 0 | G7: 0 | H7: 0 | I7: 0
B9: B. TOTALE IMMOBILIZZAZIONI sep.ind. Di quelle conc. In loc. Finanz. | C9: 34503000 | D9: 44167000 | E9: 45418000 | F9: 50058000 | G9: 73726000 | H9: 76596000 | I9: 84356000
B10: B.I. TOTALE IMMOB. IMMATERIALI | C10: 3859000 | D10: 3831000 | E10: 3838000 | F10: 3846000 | G10: 3838000 | H10: 3834000 | I10: 3824000
B11: B.I.1. Costi impianto e ampl. | C11: 0 | D11: 0 | E11: 0 | F11: 0 | G11: 0 | H11: 0 | I11: 0
B12: B.I.2. Costi ricerca e pubb. | C12: 0 | D12: 0 | E12: 0 | F12: 0 | G12: 0 | H12: 0 | I12: 0
B13: B.I.3. Diritti brevetto ind. | C13: 0 | D13: 0 | E13: 0 | F13: 0 | G13: 0 | H13: 0 | I13: 0
B14: B.I.4. Concessioni, licenze | C14: 38000 | D14: 10000 | E14: 17000 | F14: 25000 | G14: 17000 | H14: 13000 | I14: 3000
B15: B.I.5. Avviamento/Differenza di consolidamento | C15: 3821000 | D15: 3821000 | E15: 3821000 | F15: 0 | G15: 3821000 | H15: 3821000 | I15: 3821000
B16: di cui: Avviamento | C16: 3821000 | D16: 3821000 | E16: 3821000 | G16: 3821000 | H16: 3821000 | I16: 3821000
B17: B.I.6. Imm. in corso | C17: 0 | D17: 0 | E17: 0 | F17: 0 | G17: 0 | H17: 0 | I17: 0
B18: B.I.7. Altre immobiliz. Immateriali | C18: 0 | D18: 0 | E18: 0 | F18: 3821000 | G18: 0 | H18: 0 | I18: 0
B19: Fondo amm.to Immob. Immateriali | C19: 333000 | D19: 379000 | E19: 382000 | F19: 378000 | H19: 430000
B21: B.II. TOTALE IMMOB. MATERIALI | C21: 17960000 | D21: 25718000 | E21: 27100000 | F21: 31281000 | G21: 31257000 | H21: 31453000 | I21: 35954000
B22: di cui: Beni materiali concessi in locazione finanziaria
B23: B.II.1. Terreni e fabbricati | C23: 0 | D23: 0 | E23: 0 | F23: 0 | G23: 0 | H23: 0 | I23: 0
B24: B.II.2. Impianti | C24: 14704000 | D24: 0 | E24: 18668000 | F24: 26000000 | G24: 24835000 | H24: 20527000 | I24: 28887000
B25: B.II.3. Attrez. industriali | C25: 696000 | D25: 0 | E25: 1407000 | F25: 1700000 | G25: 1609000 | H25: 1694000 | I25: 2132000
B26: B.II.4. Altri beni | C26: 2560000 | D26: 25718000 | E26: 4195000 | F26: 3523000 | G26: 2935000 | H26: 2321000 | I26: 3289000
B27: B.II.5. Imm. in corso/acconti | C27: 0 | D27: 0 | E27: 2830000 | F27: 58000 | G27: 1878000 | H27: 6911000 | I27: 1646000
B28: Fondo amm.to Immob. Materiali | C28: 25896000 | D28: 30623000 | E28: 32691000 | F28: 32181000 | G28: 37337000 | H28: 43318000 | I28: 43689000
B30: B.III. TOTALE IMMOB. FINANZIARIE | C30: 12684000 | D30: 14618000 | E30: 14480000 | F30: 14931000 | G30: 38631000 | H30: 41309000 | I30: 44578000
B31: di cui: esigibili entro l'esercizio successivo | G31: 136000 | H31: 281000 | I31: 0
B32: B.III.1. TOT Partecipazioni | C32: 8626000 | D32: 11723000 | E32: 12672000 | F32: 14920000 | G32: 38484000 | H32: 41017000 | I32: 44567000
B33: B.III.1.a. Imprese controllate | C33: 8621000 | D33: 11667000 | E33: 12616000 | F33: 14914000 | G33: 38478000 | H33: 41012000 | I33: 44562000
B34: B.III.1.b. Imprese collegate | C34: 0 | D34: 0 | E34: 0 | F34: 0 | G34: 0 | H34: 0 | I34: 0
B35: B.III.1.c. Imprese controllanti | C35: 0 | D35: 0 | E35: 0 | F35: 0 | G35: 0 | H35: 0 | I35: 0
B36: B.III.1.d. In imprese sottoposte al controllo delle controllanti | F36: 0 | G36: 0 | H36: 0 | I36: 0
B37: B.III.1.d.bis. Altre imprese | C37: 5000 | D37: 56000 | E37: 56000 | F37: 6000 | G37: 6000 | H37: 5000 | I37: 5000
B38: B.III.2. TOT CREDITI Imm. Fin. | C38: 4058000 | D38: 2895000 | E38: 1808000 | F38: 11000 | G38: 147000 | H38: 292000 | I38: 11000
B39: B.III.2.a. Cred. vs Controllate entro | C39: 0 | D39: 0 | E39: 0 | F39: 0 | G39: 0 | H39: 0 | I39: 0
B40: B.III.2.a. Cred. vs Controllate oltre | C40: 4052000 | D40: 2750000 | E40: 1750000 | F40: 0 | G40: 0 | H40: 0 | I40: 0
B41: B.III.2.b. Cred. vs Collegate entro | C41: 0 | D41: 0 | E41: 0 | F41: 0 | G41: 0 | H41: 0 | I41: 0
B42: B.III.2.b. Cred. vs Collegate oltre | C42: 0 | D42: 0 | E42: 0 | F42: 0 | G42: 0 | H42: 0 | I42: 0
B43: B.III.2.c. Cred. vs Controllanti entro | C43: 0 | D43: 0 | E43: 0 | F43: 0 | G43: 136000 | H43: 281000 | I43: 0
B44: B.III.2.c. Cred. vs Controllanti oltre | C44: 0 | D44: 140000 | E44: 53000 | F44: 0 | G44: 0 | H44: 0 | I44: 0
B45: B.III.2.d. Cred. vs imprese sottoposte al controllo delle controllanti entro | F45: 0 | G45: 0 | H45: 0 | I45: 0
B46: B.III.2.d. Cred. vs imprese sottoposte al controllo delle controllanti oltre | F46: 0 | G46: 0 | H46: 0 | I46: 0
B47: B.III.2.d.bis. Cred. vs Altri entro | C47: 0 | D47: 0 | E47: 0 | F47: 0 | G47: 0 | H47: 0 | I47: 0
B48: B.III.2.d.bis Cred. vs Altri oltre | C48: 6000 | D48: 5000 | E48: 5000 | F48: 11000 | G48: 11000 | H48: 11000 | I48: 11000
B49: B.III. CREDITI FIN. A BREVE | C49: 0 | D49: 0 | E49: 0 | F49: 0 | G49: 136000 | H49: 281000 | I49: 0
B50: B.III. CREDITI FIN. A OLTRE | C50: 4058000 | D50: 2895000 | E50: 1808000 | F50: 11000 | G50: 11000 | H50: 11000 | I50: 11000
B51: B.III.3. Altri titoli | C51: 0 | D51: 0 | E51: 0 | F51: 0 | G51: 0 | H51: 0 | I51: 0
B52: B.III.3.bis. Azioni proprie | C52: 0 | D52: 0 | E52: 0 | F52: 0 | G52: 0 | H52: 0 | I52: 0
B53: B.III.4. Strumenti finanziari derivati attivi | F53: 0 | G53: 0 | H53: 0 | I53: 0
B54: Azioni proprie DI CUI: Val nominale | C54: 0 | D54: 0 | E54: 0 | F54: 0 | G54: 0 | H54: 0 | I54: 0
B56: C. ATTIVO CIRCOLANTE | C56: 23980000 | D56: 24655000 | E56: 23407000 | F56: 23549000 | G56: 21580000 | H56: 37424000 | I56: 47021000
B57: C.I. TOTALE RIMANENZE | C57: 297000 | D57: 287000 | E57: 215000 | F57: 128000 | G57: 142000 | H57: 103000 | I57: 140000
B58: C.I.1. Materie prime | C58: 297000 | D58: 287000 | E58: 215000 | F58: 128000 | G58: 142000 | H58: 103000 | I58: 140000
B59: C.I.2. Prodotti semilav./in corso | C59: 0 | D59: 0 | E59: 0 | F59: 0 | G59: 0 | H59: 0 | I59: 0
B60: C.I.3. Lavori in corso | C60: 0 | D60: 0 | E60: 0 | F60: 0 | G60: 0 | H60: 0 | I60: 0
B61: C.I.4. Prodotti finiti | C61: 0 | D61: 0 | E61: 0 | F61: 0 | G61: 0 | H61: 0 | I61: 0
B62: C.I.5. Acconti | C62: 0 | D62: 0 | E62: 0 | F62: 0 | G62: 0 | H62: 0 | I62: 0
B63: Immobilizzazioni materiali destinate alla vendita | F63: 0 | G63: 0 | H63: 0 | I63: 0
B65: C.II. TOTALE CREDITI | C65: 23569000 | D65: 23856000 | E65: 22908000 | F65: 17539000 | G65: 19057000 | H65: 17785000 | I65: 23615000
B66: C.II.1. Cred. vs Clienti entro | C66: 21377000 | D66: 12897000 | E66: 12153000 | F66: 12870000 | G66: 14732000 | H66: 13653000 | I66: 17104000
B67: C.II.1. Cred. vs Clienti oltre | C67: 0 | D67: 0 | E67: 0 | F67: 0 | G67: 0 | H67: 0 | I67: 0
B68: C.II.2. Cred. vs Controllate entro | C68: 0 | D68: 6842000 | E68: 8071000 | F68: 1949000 | G68: 1790000 | H68: 1627000 | I68: 2521000
B69: C.II.2. Cred. vs Controllate oltre | C69: 0 | D69: 0 | E69: 0 | F69: 0 | G69: 0 | H69: 0 | I69: 0
B70: C.II.3. Cred. vs Collegate entro | C70: 302000 | D70: 499000 | E70: 0 | F70: 510000 | G70: 0 | H70: 0 | I70: 592000
B71: C.II.3. Cred. vs Collegate oltre | C71: 0 | D71: 0 | E71: 0 | F71: 32000 | G71: 0 | H71: 0 | I71: 207000
B72: C.II.4. Cred. vs Controllanti entro | C72: 0 | D72: 0 | E72: 21000 | F72: 0 | G72: 0 | H72: 0 | I72: 879000
B73: C.II.4. Cred. vs Controllanti oltre | C73: 0 | D73: 0 | E73: 0 | F73: 0 | G73: 0 | H73: 0 | I73: 0
B74: C.II.5. Cred. vs imprese sottoposte al controllo delle controllanti entro | F74: 0 | G74: 0 | H74: 0 | I74: 0
B75: C.II.5. Cred. vs imprese sottoposte al controllo delle controllanti oltre | F75: 0 | G75: 0 | H75: 0 | I75: 0
B76: C.II.5.bis. Cred. tributari entro | C76: 1000 | D76: 1000 | E76: 241000 | F76: 52000 | G76: 155000 | H76: 57000 | I76: 117000
B77: C.II.5.bis. Cred. tributari oltre | C77: 0 | D77: 0 | E77: 0 | F77: 0 | G77: 0 | H77: 0 | I77: 0
B78: C.II.5.ter. Cred. per imposte anticipate entro | C78: 0 | D78: 0 | E78: 0 | F78: 0 | G78: 0 | H78: 0 | I78: 0
B79: C.II.5.ter. Cred. per imposte anticipate oltre | C79: 849000 | D79: 1022000 | E79: 1148000 | F79: 1432000 | G79: 1613000 | H79: 1906000 | I79: 1832000
B80: C.II.5.quater. Cred. verso altri entro | C80: 1040000 | D80: 2595000 | E80: 1274000 | F80: 694000 | G80: 767000 | H80: 542000 | I80: 363000
B81: C.II.5.quater. Cred. verso altri oltre | C81: 0 | D81: 0 | E81: 0 | F81: 0 | G81: 0 | H81: 0 | I81: 0
B82: C.II. Crediti a breve | C82: 22720000 | D82: 22834000 | E82: 21760000 | F82: 16075000 | G82: 17444000 | H82: 15879000 | I82: 21576000
B83: Crediti per imposte anticipate
B84: C.II. Crediti a oltre | C84: 849000 | D84: 1022000 | E84: 1148000 | F84: 1464000 | G84: 1613000 | H84: 1906000 | I84: 2039000
B86: C.III. TOTALE ATTIVITA' FINANZIARIE | C86: 3000 | D86: 2000 | E86: 1000 | F86: 2894000 | G86: 2044000 | H86: 19331000 | I86: 23165000
B87: C.III.1. Partec.ni in Controllate | C87: 0 | D87: 0 | E87: 0 | F87: 0 | G87: 0 | H87: 0 | I87: 0
B88: C.III.2. Partec.ni in Collegate | C88: 0 | D88: 0 | E88: 0 | F88: 0 | G88: 0 | H88: 0 | I88: 0
B89: C.III.3. Partec.ni in Controllanti | C89: 0 | D89: 0 | E89: 0 | F89: 0 | G89: 0 | H89: 0 | I89: 0
B90: C.III.3.bis. Partec.ni in imprese sottoposte al controllo delle controllanti | F90: 0 | G90: 0 | H90: 0 | I90: 0
B91: C.III.4. Altre Partec.ni | C91: 0 | D91: 0 | E91: 0 | F91: 0 | G91: 0 | H91: 0 | I91: 0
B92: C.III.4.bis. Azioni proprie | C92: 0 | D92: 0 | E92: 0 | F92: 0 | G92: 0 | H92: 0 | I92: 0
B93: Azioni proprie DI CUI: Val nominale | C93: 0 | D93: 0 | E93: 0 | F93: 0 | G93: 0 | H93: 0 | I93: 0
B94: C.III.5. Strumenti finanziari derivati attivi | F94: 1000 | G94: 1000 | H94: 1000 | I94: 0
B95: C.III.6. Altri titoli | C95: 3000 | D95: 2000 | E95: 1000 | F95: 0 | G95: 0 | H95: 0 | I95: 0
B96: C.III.7. Attività finanziarie per la gestione accentrata della tesoreria | F96: 2893000 | G96: 2043000 | H96: 19330000 | I96: 23165000
B98: C.IV. TOT. DISPON. LIQUIDE | C98: 111000 | D98: 510000 | E98: 283000 | F98: 2988000 | G98: 337000 | H98: 205000 | I98: 101000
B99: C.IV.1. Depositi bancari | C99: 101000 | D99: 499000 | E99: 271000 | F99: 2972000 | G99: 300000 | H99: 179000 | I99: 91000
B100: C.IV.2. Assegni | C100: 0 | D100: 0 | E100: 0 | F100: 0 | G100: 0 | H100: 0 | I100: 0
B101: C.IV.3. Denaro in cassa | C101: 10000 | D101: 11000 | E101: 12000 | F101: 16000 | G101: 37000 | H101: 26000 | I101: 10000
B103: D. RATEI E RISCONTI | C103: 0 | D103: 0 | E103: 0 | F103: 0 | G103: 0 | H103: 0 | I103: 0
B104: Disaggio su prestiti | C104: 0 | D104: 0 | E104: 0 | F104: 0 | G104: 0 | H104: 0 | I104: 0
B106: TOTALE ATTIVO | C106: 58483000 | D106: 68822000 | E106: 68825000 | F106: 73607000 | G106: 95306000 | H106: 114020000 | I106: 131377000
B108: Passivo
B110: PATRIMONIO NETTO
B112: A. TOTALE PATRIMONIO NETTO | C112: 17007000 | D112: 19695000 | E112: 22872000 | F112: 24689000 | G112: 28757000 | H112: 32528000 | I112: 36461000
B113: A.I. Capitale sociale | C113: 700000 | D113: 700000 | E113: 700000 | F113: 700000 | G113: 700000 | H113: 700000 | I113: 700000
B114: di cui: Versamenti soci in c/capitale | C114: 8291000 | D114: 8291000 | E114: 8291000 | G114: 8291000 | H114: 8291000 | I114: 0
...
